<?xml version="1.0" encoding="UTF-8" standalone="no"?>
<XMLDefinition Generator="Iron Speed Designer" Version="12.2" Type="VIEW">
  <ColumnDefinition>
    <Column InternalName="0" Priority="1" ColumnNum="0">
      <columnName>exchange_inventory_id</columnName>
      <columnUIName>%ISD_DEFAULT%</columnUIName>
      <columnType>Number</columnType>
      <columnDBType>numeric</columnDBType>
      <columnLengthSet>18.0</columnLengthSet>
      <columnDefault>
      </columnDefault>
      <columnDBDefault>
      </columnDBDefault>
      <columnIndex>N</columnIndex>
      <columnUnique>N</columnUnique>
      <columnFunction>
      </columnFunction>
      <columnDBFormat>
      </columnDBFormat>
      <columnPK>N</columnPK>
      <columnPermanent>N</columnPermanent>
      <columnComputed>N</columnComputed>
      <columnIdentity>N</columnIdentity>
      <columnReadOnly>N</columnReadOnly>
      <columnRequired>N</columnRequired>
      <columnNotNull>N</columnNotNull>
      <columnCaseSensitive>N</columnCaseSensitive>
      <columnCollation>
      </columnCollation>
      <columnFullText>N</columnFullText>
      <columnVisibleWidth>%ISD_DEFAULT%</columnVisibleWidth>
      <columnTableAliasName>
      </columnTableAliasName>
      <applyLabelText>Y</applyLabelText>
    </Column>
    <Column InternalName="1" Priority="2" ColumnNum="1">
      <columnName>date_received</columnName>
      <columnUIName>%ISD_DEFAULT%</columnUIName>
      <columnType>Date</columnType>
      <columnDBType>date</columnDBType>
      <columnLengthSet>
      </columnLengthSet>
      <columnDefault>
      </columnDefault>
      <columnDBDefault>
      </columnDBDefault>
      <columnIndex>N</columnIndex>
      <columnUnique>N</columnUnique>
      <columnFunction>notrim</columnFunction>
      <columnFormat>d</columnFormat>
      <columnDBFormat>d</columnDBFormat>
      <columnPK>N</columnPK>
      <columnPermanent>N</columnPermanent>
      <columnComputed>N</columnComputed>
      <columnIdentity>N</columnIdentity>
      <columnReadOnly>N</columnReadOnly>
      <columnRequired>N</columnRequired>
      <columnNotNull>N</columnNotNull>
      <columnCaseSensitive>N</columnCaseSensitive>
      <columnCollation>
      </columnCollation>
      <columnFullText>N</columnFullText>
      <columnVisibleWidth>%ISD_DEFAULT%</columnVisibleWidth>
      <columnTableAliasName>
      </columnTableAliasName>
      <applyLabelText>Y</applyLabelText>
    </Column>
    <Column InternalName="2" Priority="3" ColumnNum="2">
      <columnName>received_customer</columnName>
      <columnUIName>%ISD_DEFAULT%</columnUIName>
      <columnType>Number</columnType>
      <columnDBType>int</columnDBType>
      <columnLengthSet>10.0</columnLengthSet>
      <columnDefault>
      </columnDefault>
      <columnDBDefault>
      </columnDBDefault>
      <columnIndex>N</columnIndex>
      <columnUnique>N</columnUnique>
      <columnFunction>
      </columnFunction>
      <columnDBFormat>
      </columnDBFormat>
      <columnPK>N</columnPK>
      <columnPermanent>N</columnPermanent>
      <columnComputed>N</columnComputed>
      <columnIdentity>N</columnIdentity>
      <columnReadOnly>N</columnReadOnly>
      <columnRequired>N</columnRequired>
      <columnNotNull>N</columnNotNull>
      <columnCaseSensitive>N</columnCaseSensitive>
      <columnCollation>
      </columnCollation>
      <columnFullText>N</columnFullText>
      <columnVisibleWidth>%ISD_DEFAULT%</columnVisibleWidth>
      <columnTableAliasName>
      </columnTableAliasName>
      <applyLabelText>Y</applyLabelText>
    </Column>
    <Column InternalName="3" Priority="4" ColumnNum="3">
      <columnName>received_from_contact_id</columnName>
      <columnUIName>%ISD_DEFAULT%</columnUIName>
      <columnType>Number</columnType>
      <columnDBType>int</columnDBType>
      <columnLengthSet>10.0</columnLengthSet>
      <columnDefault>
      </columnDefault>
      <columnDBDefault>
      </columnDBDefault>
      <columnIndex>N</columnIndex>
      <columnUnique>N</columnUnique>
      <columnFunction>
      </columnFunction>
      <columnDBFormat>
      </columnDBFormat>
      <columnPK>N</columnPK>
      <columnPermanent>N</columnPermanent>
      <columnComputed>N</columnComputed>
      <columnIdentity>N</columnIdentity>
      <columnReadOnly>N</columnReadOnly>
      <columnRequired>N</columnRequired>
      <columnNotNull>N</columnNotNull>
      <columnCaseSensitive>N</columnCaseSensitive>
      <columnCollation>
      </columnCollation>
      <columnFullText>N</columnFullText>
      <columnVisibleWidth>%ISD_DEFAULT%</columnVisibleWidth>
      <columnTableAliasName>
      </columnTableAliasName>
      <applyLabelText>Y</applyLabelText>
    </Column>
    <Column InternalName="4" Priority="5" ColumnNum="4">
      <columnName>make_id</columnName>
      <columnUIName>%ISD_DEFAULT%</columnUIName>
      <columnType>String</columnType>
      <columnDBType>nvarchar</columnDBType>
      <columnLengthSet>30</columnLengthSet>
      <columnDefault>
      </columnDefault>
      <columnDBDefault>
      </columnDBDefault>
      <columnIndex>N</columnIndex>
      <columnUnique>N</columnUnique>
      <columnFunction>
      </columnFunction>
      <columnDBFormat>
      </columnDBFormat>
      <columnPK>N</columnPK>
      <columnPermanent>N</columnPermanent>
      <columnComputed>N</columnComputed>
      <columnIdentity>N</columnIdentity>
      <columnReadOnly>N</columnReadOnly>
      <columnRequired>N</columnRequired>
      <columnNotNull>N</columnNotNull>
      <columnCaseSensitive Source="Database">N</columnCaseSensitive>
      <columnCollation>SQL_Latin1_General_CP1_CI_AS</columnCollation>
      <columnFullText>N</columnFullText>
      <columnVisibleWidth>%ISD_DEFAULT%</columnVisibleWidth>
      <columnTableAliasName>
      </columnTableAliasName>
      <applyLabelText>Y</applyLabelText>
    </Column>
    <Column InternalName="5" Priority="6" ColumnNum="5">
      <columnName>model_id</columnName>
      <columnUIName>%ISD_DEFAULT%</columnUIName>
      <columnType>String</columnType>
      <columnDBType>nvarchar</columnDBType>
      <columnLengthSet>40</columnLengthSet>
      <columnDefault>
      </columnDefault>
      <columnDBDefault>
      </columnDBDefault>
      <columnIndex>N</columnIndex>
      <columnUnique>N</columnUnique>
      <columnFunction>
      </columnFunction>
      <columnDBFormat>
      </columnDBFormat>
      <columnPK>N</columnPK>
      <columnPermanent>N</columnPermanent>
      <columnComputed>N</columnComputed>
      <columnIdentity>N</columnIdentity>
      <columnReadOnly>N</columnReadOnly>
      <columnRequired>N</columnRequired>
      <columnNotNull>N</columnNotNull>
      <columnCaseSensitive Source="Database">N</columnCaseSensitive>
      <columnCollation>SQL_Latin1_General_CP1_CI_AS</columnCollation>
      <columnFullText>N</columnFullText>
      <columnVisibleWidth>%ISD_DEFAULT%</columnVisibleWidth>
      <columnTableAliasName>
      </columnTableAliasName>
      <applyLabelText>Y</applyLabelText>
    </Column>
    <Column InternalName="6" Priority="7" ColumnNum="6">
      <columnName>serial_number</columnName>
      <columnUIName>%ISD_DEFAULT%</columnUIName>
      <columnType>String</columnType>
      <columnDBType>varchar</columnDBType>
      <columnLengthSet>25</columnLengthSet>
      <columnDefault>
      </columnDefault>
      <columnDBDefault>
      </columnDBDefault>
      <columnIndex>N</columnIndex>
      <columnUnique>N</columnUnique>
      <columnFunction>
      </columnFunction>
      <columnDBFormat>
      </columnDBFormat>
      <columnPK>N</columnPK>
      <columnPermanent>N</columnPermanent>
      <columnComputed>N</columnComputed>
      <columnIdentity>N</columnIdentity>
      <columnReadOnly>N</columnReadOnly>
      <columnRequired>N</columnRequired>
      <columnNotNull>N</columnNotNull>
      <columnCaseSensitive Source="Database">N</columnCaseSensitive>
      <columnCollation>SQL_Latin1_General_CP1_CI_AS</columnCollation>
      <columnFullText>N</columnFullText>
      <columnVisibleWidth>%ISD_DEFAULT%</columnVisibleWidth>
      <columnTableAliasName>
      </columnTableAliasName>
      <applyLabelText>Y</applyLabelText>
    </Column>
    <Column InternalName="7" Priority="8" ColumnNum="7">
      <columnName>customer_ein</columnName>
      <columnUIName>%ISD_DEFAULT%</columnUIName>
      <columnType>String</columnType>
      <columnDBType>varchar</columnDBType>
      <columnLengthSet>15</columnLengthSet>
      <columnDefault>
      </columnDefault>
      <columnDBDefault>
      </columnDBDefault>
      <columnIndex>N</columnIndex>
      <columnUnique>N</columnUnique>
      <columnFunction>
      </columnFunction>
      <columnDBFormat>
      </columnDBFormat>
      <columnPK>N</columnPK>
      <columnPermanent>N</columnPermanent>
      <columnComputed>N</columnComputed>
      <columnIdentity>N</columnIdentity>
      <columnReadOnly>N</columnReadOnly>
      <columnRequired>N</columnRequired>
      <columnNotNull>N</columnNotNull>
      <columnCaseSensitive Source="Database">N</columnCaseSensitive>
      <columnCollation>SQL_Latin1_General_CP1_CI_AS</columnCollation>
      <columnFullText>N</columnFullText>
      <columnVisibleWidth>%ISD_DEFAULT%</columnVisibleWidth>
      <columnTableAliasName>
      </columnTableAliasName>
      <applyLabelText>Y</applyLabelText>
    </Column>
    <Column InternalName="8" Priority="9" ColumnNum="8">
      <columnName>other_id_num</columnName>
      <columnUIName>%ISD_DEFAULT%</columnUIName>
      <columnType>String</columnType>
      <columnDBType>varchar</columnDBType>
      <columnLengthSet>25</columnLengthSet>
      <columnDefault>
      </columnDefault>
      <columnDBDefault>
      </columnDBDefault>
      <columnIndex>N</columnIndex>
      <columnUnique>N</columnUnique>
      <columnFunction>
      </columnFunction>
      <columnDBFormat>
      </columnDBFormat>
      <columnPK>N</columnPK>
      <columnPermanent>N</columnPermanent>
      <columnComputed>N</columnComputed>
      <columnIdentity>N</columnIdentity>
      <columnReadOnly>N</columnReadOnly>
      <columnRequired>N</columnRequired>
      <columnNotNull>N</columnNotNull>
      <columnCaseSensitive Source="Database">N</columnCaseSensitive>
      <columnCollation>SQL_Latin1_General_CP1_CI_AS</columnCollation>
      <columnFullText>N</columnFullText>
      <columnVisibleWidth>%ISD_DEFAULT%</columnVisibleWidth>
      <columnTableAliasName>
      </columnTableAliasName>
      <applyLabelText>Y</applyLabelText>
    </Column>
    <Column InternalName="9" Priority="10" ColumnNum="9">
      <columnName>description</columnName>
      <columnUIName>%ISD_DEFAULT%</columnUIName>
      <columnType>String</columnType>
      <columnDBType>varchar</columnDBType>
      <columnLengthSet>750</columnLengthSet>
      <columnDefault>
      </columnDefault>
      <columnDBDefault>
      </columnDBDefault>
      <columnIndex>N</columnIndex>
      <columnUnique>N</columnUnique>
      <columnFunction>
      </columnFunction>
      <columnDBFormat>
      </columnDBFormat>
      <columnPK>N</columnPK>
      <columnPermanent>N</columnPermanent>
      <columnComputed>N</columnComputed>
      <columnIdentity>N</columnIdentity>
      <columnReadOnly>N</columnReadOnly>
      <columnRequired>N</columnRequired>
      <columnNotNull>N</columnNotNull>
      <columnCaseSensitive Source="Database">N</columnCaseSensitive>
      <columnCollation>SQL_Latin1_General_CP1_CI_AS</columnCollation>
      <columnFullText>N</columnFullText>
      <columnVisibleWidth>%ISD_DEFAULT%</columnVisibleWidth>
      <columnTableAliasName>
      </columnTableAliasName>
      <applyLabelText>Y</applyLabelText>
    </Column>
    <Column InternalName="10" Priority="11" ColumnNum="10">
      <columnName>category_id</columnName>
      <columnUIName>%ISD_DEFAULT%</columnUIName>
      <columnType>String</columnType>
      <columnDBType>nvarchar</columnDBType>
      <columnLengthSet>50</columnLengthSet>
      <columnDefault>
      </columnDefault>
      <columnDBDefault>
      </columnDBDefault>
      <columnIndex>N</columnIndex>
      <columnUnique>N</columnUnique>
      <columnFunction>
      </columnFunction>
      <columnDBFormat>
      </columnDBFormat>
      <columnPK>N</columnPK>
      <columnPermanent>N</columnPermanent>
      <columnComputed>N</columnComputed>
      <columnIdentity>N</columnIdentity>
      <columnReadOnly>N</columnReadOnly>
      <columnRequired>N</columnRequired>
      <columnNotNull>N</columnNotNull>
      <columnCaseSensitive Source="Database">N</columnCaseSensitive>
      <columnCollation>SQL_Latin1_General_CP1_CI_AS</columnCollation>
      <columnFullText>N</columnFullText>
      <columnVisibleWidth>%ISD_DEFAULT%</columnVisibleWidth>
      <columnTableAliasName>
      </columnTableAliasName>
      <applyLabelText>Y</applyLabelText>
    </Column>
    <Column InternalName="11" Priority="12" ColumnNum="11">
      <columnName>repair_notes</columnName>
      <columnUIName>%ISD_DEFAULT%</columnUIName>
      <columnType>String</columnType>
      <columnDBType>varchar</columnDBType>
      <columnLengthSet>1000</columnLengthSet>
      <columnDefault>
      </columnDefault>
      <columnDBDefault>
      </columnDBDefault>
      <columnIndex>N</columnIndex>
      <columnUnique>N</columnUnique>
      <columnFunction>
      </columnFunction>
      <columnDBFormat>
      </columnDBFormat>
      <columnPK>N</columnPK>
      <columnPermanent>N</columnPermanent>
      <columnComputed>N</columnComputed>
      <columnIdentity>N</columnIdentity>
      <columnReadOnly>N</columnReadOnly>
      <columnRequired>N</columnRequired>
      <columnNotNull>N</columnNotNull>
      <columnCaseSensitive Source="Database">N</columnCaseSensitive>
      <columnCollation>SQL_Latin1_General_CP1_CI_AS</columnCollation>
      <columnFullText>N</columnFullText>
      <columnVisibleWidth>%ISD_DEFAULT%</columnVisibleWidth>
      <columnTableAliasName>
      </columnTableAliasName>
      <applyLabelText>Y</applyLabelText>
    </Column>
    <Column InternalName="12" Priority="13" ColumnNum="12">
      <columnName>condition_id</columnName>
      <columnUIName>%ISD_DEFAULT%</columnUIName>
      <columnType>String</columnType>
      <columnDBType>nvarchar</columnDBType>
      <columnLengthSet>20</columnLengthSet>
      <columnDefault>
      </columnDefault>
      <columnDBDefault>
      </columnDBDefault>
      <columnIndex>N</columnIndex>
      <columnUnique>N</columnUnique>
      <columnFunction>
      </columnFunction>
      <columnDBFormat>
      </columnDBFormat>
      <columnPK>N</columnPK>
      <columnPermanent>N</columnPermanent>
      <columnComputed>N</columnComputed>
      <columnIdentity>N</columnIdentity>
      <columnReadOnly>N</columnReadOnly>
      <columnRequired>N</columnRequired>
      <columnNotNull>N</columnNotNull>
      <columnCaseSensitive Source="Database">N</columnCaseSensitive>
      <columnCollation>SQL_Latin1_General_CP1_CI_AS</columnCollation>
      <columnFullText>N</columnFullText>
      <columnVisibleWidth>%ISD_DEFAULT%</columnVisibleWidth>
      <columnTableAliasName>
      </columnTableAliasName>
      <applyLabelText>Y</applyLabelText>
    </Column>
    <Column InternalName="13" Priority="14" ColumnNum="13">
      <columnName>require_accessories</columnName>
      <columnUIName>%ISD_DEFAULT%</columnUIName>
      <columnType>Boolean</columnType>
      <columnDBType>bit</columnDBType>
      <columnLengthSet>
      </columnLengthSet>
      <columnDefault>
      </columnDefault>
      <columnDBDefault>
      </columnDBDefault>
      <columnIndex>N</columnIndex>
      <columnUnique>N</columnUnique>
      <columnFunction>
      </columnFunction>
      <columnDBFormat>
      </columnDBFormat>
      <columnPK>N</columnPK>
      <columnPermanent>N</columnPermanent>
      <columnComputed>N</columnComputed>
      <columnIdentity>N</columnIdentity>
      <columnReadOnly>N</columnReadOnly>
      <columnRequired>N</columnRequired>
      <columnNotNull>N</columnNotNull>
      <columnCaseSensitive>N</columnCaseSensitive>
      <columnCollation>
      </columnCollation>
      <columnFullText>N</columnFullText>
      <columnVisibleWidth>%ISD_DEFAULT%</columnVisibleWidth>
      <columnTableAliasName>
      </columnTableAliasName>
      <applyLabelText>Y</applyLabelText>
    </Column>
    <Column InternalName="14" Priority="15" ColumnNum="14">
      <columnName>equipment_phi</columnName>
      <columnUIName>%ISD_DEFAULT%</columnUIName>
      <columnType>Boolean</columnType>
      <columnDBType>bit</columnDBType>
      <columnLengthSet>
      </columnLengthSet>
      <columnDefault>
      </columnDefault>
      <columnDBDefault>
      </columnDBDefault>
      <columnIndex>N</columnIndex>
      <columnUnique>N</columnUnique>
      <columnFunction>
      </columnFunction>
      <columnDBFormat>
      </columnDBFormat>
      <columnPK>N</columnPK>
      <columnPermanent>N</columnPermanent>
      <columnComputed>N</columnComputed>
      <columnIdentity>N</columnIdentity>
      <columnReadOnly>N</columnReadOnly>
      <columnRequired>N</columnRequired>
      <columnNotNull>N</columnNotNull>
      <columnCaseSensitive>N</columnCaseSensitive>
      <columnCollation>
      </columnCollation>
      <columnFullText>N</columnFullText>
      <columnVisibleWidth>%ISD_DEFAULT%</columnVisibleWidth>
      <columnTableAliasName>
      </columnTableAliasName>
      <applyLabelText>Y</applyLabelText>
    </Column>
    <Column InternalName="15" Priority="16" ColumnNum="15">
      <columnName>purchase_price</columnName>
      <columnUIName>%ISD_DEFAULT%</columnUIName>
      <columnType>Currency</columnType>
      <columnDBType>money</columnDBType>
      <columnLengthSet>19.4</columnLengthSet>
      <columnDefault>
      </columnDefault>
      <columnDBDefault>
      </columnDBDefault>
      <columnIndex>N</columnIndex>
      <columnUnique>N</columnUnique>
      <columnFunction>
      </columnFunction>
      <columnFormat>C</columnFormat>
      <columnDBFormat>C</columnDBFormat>
      <columnPK>N</columnPK>
      <columnPermanent>N</columnPermanent>
      <columnComputed>N</columnComputed>
      <columnIdentity>N</columnIdentity>
      <columnReadOnly>N</columnReadOnly>
      <columnRequired>N</columnRequired>
      <columnNotNull>N</columnNotNull>
      <columnCaseSensitive>N</columnCaseSensitive>
      <columnCollation>
      </columnCollation>
      <columnFullText>N</columnFullText>
      <columnVisibleWidth>%ISD_DEFAULT%</columnVisibleWidth>
      <columnTableAliasName>
      </columnTableAliasName>
      <applyLabelText>Y</applyLabelText>
    </Column>
    <Column InternalName="16" Priority="17" ColumnNum="16">
      <columnName>pd_date</columnName>
      <columnUIName>%ISD_DEFAULT%</columnUIName>
      <columnType>Date</columnType>
      <columnDBType>date</columnDBType>
      <columnLengthSet>
      </columnLengthSet>
      <columnDefault>
      </columnDefault>
      <columnDBDefault>
      </columnDBDefault>
      <columnIndex>N</columnIndex>
      <columnUnique>N</columnUnique>
      <columnFunction>notrim</columnFunction>
      <columnFormat>d</columnFormat>
      <columnDBFormat>d</columnDBFormat>
      <columnPK>N</columnPK>
      <columnPermanent>N</columnPermanent>
      <columnComputed>N</columnComputed>
      <columnIdentity>N</columnIdentity>
      <columnReadOnly>N</columnReadOnly>
      <columnRequired>N</columnRequired>
      <columnNotNull>N</columnNotNull>
      <columnCaseSensitive>N</columnCaseSensitive>
      <columnCollation>
      </columnCollation>
      <columnFullText>N</columnFullText>
      <columnVisibleWidth>%ISD_DEFAULT%</columnVisibleWidth>
      <columnTableAliasName>
      </columnTableAliasName>
      <applyLabelText>Y</applyLabelText>
    </Column>
    <Column InternalName="17" Priority="18" ColumnNum="17">
      <columnName>doc_num</columnName>
      <columnUIName>%ISD_DEFAULT%</columnUIName>
      <columnType>String</columnType>
      <columnDBType>varchar</columnDBType>
      <columnLengthSet>25</columnLengthSet>
      <columnDefault>
      </columnDefault>
      <columnDBDefault>
      </columnDBDefault>
      <columnIndex>N</columnIndex>
      <columnUnique>N</columnUnique>
      <columnFunction>
      </columnFunction>
      <columnDBFormat>
      </columnDBFormat>
      <columnPK>N</columnPK>
      <columnPermanent>N</columnPermanent>
      <columnComputed>N</columnComputed>
      <columnIdentity>N</columnIdentity>
      <columnReadOnly>N</columnReadOnly>
      <columnRequired>N</columnRequired>
      <columnNotNull>N</columnNotNull>
      <columnCaseSensitive Source="Database">N</columnCaseSensitive>
      <columnCollation>SQL_Latin1_General_CP1_CI_AS</columnCollation>
      <columnFullText>N</columnFullText>
      <columnVisibleWidth>%ISD_DEFAULT%</columnVisibleWidth>
      <columnTableAliasName>
      </columnTableAliasName>
      <applyLabelText>Y</applyLabelText>
    </Column>
    <Column InternalName="18" Priority="19" ColumnNum="18">
      <columnName>disposition_id</columnName>
      <columnUIName>%ISD_DEFAULT%</columnUIName>
      <columnType>Number</columnType>
      <columnDBType>numeric</columnDBType>
      <columnLengthSet>18.0</columnLengthSet>
      <columnDefault>
      </columnDefault>
      <columnDBDefault>
      </columnDBDefault>
      <columnIndex>N</columnIndex>
      <columnUnique>N</columnUnique>
      <columnFunction>
      </columnFunction>
      <columnDBFormat>
      </columnDBFormat>
      <columnPK>N</columnPK>
      <columnPermanent>N</columnPermanent>
      <columnComputed>N</columnComputed>
      <columnIdentity>N</columnIdentity>
      <columnReadOnly>N</columnReadOnly>
      <columnRequired>N</columnRequired>
      <columnNotNull>N</columnNotNull>
      <columnCaseSensitive>N</columnCaseSensitive>
      <columnCollation>
      </columnCollation>
      <columnFullText>N</columnFullText>
      <columnVisibleWidth>%ISD_DEFAULT%</columnVisibleWidth>
      <columnTableAliasName>
      </columnTableAliasName>
      <applyLabelText>Y</applyLabelText>
    </Column>
    <Column InternalName="19" Priority="20" ColumnNum="19">
      <columnName>sale_method_id</columnName>
      <columnUIName>%ISD_DEFAULT%</columnUIName>
      <columnType>Number</columnType>
      <columnDBType>numeric</columnDBType>
      <columnLengthSet>18.0</columnLengthSet>
      <columnDefault>
      </columnDefault>
      <columnDBDefault>
      </columnDBDefault>
      <columnIndex>N</columnIndex>
      <columnUnique>N</columnUnique>
      <columnFunction>
      </columnFunction>
      <columnDBFormat>
      </columnDBFormat>
      <columnPK>N</columnPK>
      <columnPermanent>N</columnPermanent>
      <columnComputed>N</columnComputed>
      <columnIdentity>N</columnIdentity>
      <columnReadOnly>N</columnReadOnly>
      <columnRequired>N</columnRequired>
      <columnNotNull>N</columnNotNull>
      <columnCaseSensitive>N</columnCaseSensitive>
      <columnCollation>
      </columnCollation>
      <columnFullText>N</columnFullText>
      <columnVisibleWidth>%ISD_DEFAULT%</columnVisibleWidth>
      <columnTableAliasName>
      </columnTableAliasName>
      <applyLabelText>Y</applyLabelText>
    </Column>
    <Column InternalName="20" Priority="21" ColumnNum="20">
      <columnName>proposed_sale_price</columnName>
      <columnUIName>%ISD_DEFAULT%</columnUIName>
      <columnType>Currency</columnType>
      <columnDBType>money</columnDBType>
      <columnLengthSet>19.4</columnLengthSet>
      <columnDefault>
      </columnDefault>
      <columnDBDefault>
      </columnDBDefault>
      <columnIndex>N</columnIndex>
      <columnUnique>N</columnUnique>
      <columnFunction>
      </columnFunction>
      <columnFormat>C</columnFormat>
      <columnDBFormat>C</columnDBFormat>
      <columnPK>N</columnPK>
      <columnPermanent>N</columnPermanent>
      <columnComputed>N</columnComputed>
      <columnIdentity>N</columnIdentity>
      <columnReadOnly>N</columnReadOnly>
      <columnRequired>N</columnRequired>
      <columnNotNull>N</columnNotNull>
      <columnCaseSensitive>N</columnCaseSensitive>
      <columnCollation>
      </columnCollation>
      <columnFullText>N</columnFullText>
      <columnVisibleWidth>%ISD_DEFAULT%</columnVisibleWidth>
      <columnTableAliasName>
      </columnTableAliasName>
      <applyLabelText>Y</applyLabelText>
    </Column>
    <Column InternalName="21" Priority="22" ColumnNum="21">
      <columnName>date_sold</columnName>
      <columnUIName>%ISD_DEFAULT%</columnUIName>
      <columnType>Date</columnType>
      <columnDBType>date</columnDBType>
      <columnLengthSet>
      </columnLengthSet>
      <columnDefault>
      </columnDefault>
      <columnDBDefault>
      </columnDBDefault>
      <columnIndex>N</columnIndex>
      <columnUnique>N</columnUnique>
      <columnFunction>notrim</columnFunction>
      <columnFormat>d</columnFormat>
      <columnDBFormat>d</columnDBFormat>
      <columnPK>N</columnPK>
      <columnPermanent>N</columnPermanent>
      <columnComputed>N</columnComputed>
      <columnIdentity>N</columnIdentity>
      <columnReadOnly>N</columnReadOnly>
      <columnRequired>N</columnRequired>
      <columnNotNull>N</columnNotNull>
      <columnCaseSensitive>N</columnCaseSensitive>
      <columnCollation>
      </columnCollation>
      <columnFullText>N</columnFullText>
      <columnVisibleWidth>%ISD_DEFAULT%</columnVisibleWidth>
      <columnTableAliasName>
      </columnTableAliasName>
      <applyLabelText>Y</applyLabelText>
    </Column>
    <Column InternalName="22" Priority="23" ColumnNum="22">
      <columnName>date_disposed</columnName>
      <columnUIName>%ISD_DEFAULT%</columnUIName>
      <columnType>Date</columnType>
      <columnDBType>date</columnDBType>
      <columnLengthSet>
      </columnLengthSet>
      <columnDefault>
      </columnDefault>
      <columnDBDefault>
      </columnDBDefault>
      <columnIndex>N</columnIndex>
      <columnUnique>N</columnUnique>
      <columnFunction>notrim</columnFunction>
      <columnFormat>d</columnFormat>
      <columnDBFormat>d</columnDBFormat>
      <columnPK>N</columnPK>
      <columnPermanent>N</columnPermanent>
      <columnComputed>N</columnComputed>
      <columnIdentity>N</columnIdentity>
      <columnReadOnly>N</columnReadOnly>
      <columnRequired>N</columnRequired>
      <columnNotNull>N</columnNotNull>
      <columnCaseSensitive>N</columnCaseSensitive>
      <columnCollation>
      </columnCollation>
      <columnFullText>N</columnFullText>
      <columnVisibleWidth>%ISD_DEFAULT%</columnVisibleWidth>
      <columnTableAliasName>
      </columnTableAliasName>
      <applyLabelText>Y</applyLabelText>
    </Column>
    <Column InternalName="23" Priority="24" ColumnNum="23">
      <columnName>sold_from_id</columnName>
      <columnUIName>%ISD_DEFAULT%</columnUIName>
      <columnType>Number</columnType>
      <columnDBType>numeric</columnDBType>
      <columnLengthSet>18.0</columnLengthSet>
      <columnDefault>
      </columnDefault>
      <columnDBDefault>
      </columnDBDefault>
      <columnIndex>N</columnIndex>
      <columnUnique>N</columnUnique>
      <columnFunction>
      </columnFunction>
      <columnDBFormat>
      </columnDBFormat>
      <columnPK>N</columnPK>
      <columnPermanent>N</columnPermanent>
      <columnComputed>N</columnComputed>
      <columnIdentity>N</columnIdentity>
      <columnReadOnly>N</columnReadOnly>
      <columnRequired>N</columnRequired>
      <columnNotNull>N</columnNotNull>
      <columnCaseSensitive>N</columnCaseSensitive>
      <columnCollation>
      </columnCollation>
      <columnFullText>N</columnFullText>
      <columnVisibleWidth>%ISD_DEFAULT%</columnVisibleWidth>
      <columnTableAliasName>
      </columnTableAliasName>
      <applyLabelText>Y</applyLabelText>
    </Column>
    <Column InternalName="24" Priority="25" ColumnNum="24">
      <columnName>final_sale_price</columnName>
      <columnUIName>%ISD_DEFAULT%</columnUIName>
      <columnType>Currency</columnType>
      <columnDBType>money</columnDBType>
      <columnLengthSet>19.4</columnLengthSet>
      <columnDefault>
      </columnDefault>
      <columnDBDefault>
      </columnDBDefault>
      <columnIndex>N</columnIndex>
      <columnUnique>N</columnUnique>
      <columnFunction>
      </columnFunction>
      <columnFormat>C</columnFormat>
      <columnDBFormat>C</columnDBFormat>
      <columnPK>N</columnPK>
      <columnPermanent>N</columnPermanent>
      <columnComputed>N</columnComputed>
      <columnIdentity>N</columnIdentity>
      <columnReadOnly>N</columnReadOnly>
      <columnRequired>N</columnRequired>
      <columnNotNull>N</columnNotNull>
      <columnCaseSensitive>N</columnCaseSensitive>
      <columnCollation>
      </columnCollation>
      <columnFullText>N</columnFullText>
      <columnVisibleWidth>%ISD_DEFAULT%</columnVisibleWidth>
      <columnTableAliasName>
      </columnTableAliasName>
      <applyLabelText>Y</applyLabelText>
    </Column>
    <Column InternalName="25" Priority="26" ColumnNum="25">
      <columnName>warehouse_id</columnName>
      <columnUIName>%ISD_DEFAULT%</columnUIName>
      <columnType>Number</columnType>
      <columnDBType>numeric</columnDBType>
      <columnLengthSet>18.0</columnLengthSet>
      <columnDefault>
      </columnDefault>
      <columnDBDefault>
      </columnDBDefault>
      <columnIndex>N</columnIndex>
      <columnUnique>N</columnUnique>
      <columnFunction>
      </columnFunction>
      <columnDBFormat>
      </columnDBFormat>
      <columnPK>N</columnPK>
      <columnPermanent>N</columnPermanent>
      <columnComputed>N</columnComputed>
      <columnIdentity>N</columnIdentity>
      <columnReadOnly>N</columnReadOnly>
      <columnRequired>N</columnRequired>
      <columnNotNull>N</columnNotNull>
      <columnCaseSensitive>N</columnCaseSensitive>
      <columnCollation>
      </columnCollation>
      <columnFullText>N</columnFullText>
      <columnVisibleWidth>%ISD_DEFAULT%</columnVisibleWidth>
      <columnTableAliasName>
      </columnTableAliasName>
      <applyLabelText>Y</applyLabelText>
    </Column>
    <Column InternalName="26" Priority="27" ColumnNum="26">
      <columnName>warehouse_location_id</columnName>
      <columnUIName>%ISD_DEFAULT%</columnUIName>
      <columnType>Number</columnType>
      <columnDBType>numeric</columnDBType>
      <columnLengthSet>18.0</columnLengthSet>
      <columnDefault>
      </columnDefault>
      <columnDBDefault>
      </columnDBDefault>
      <columnIndex>N</columnIndex>
      <columnUnique>N</columnUnique>
      <columnFunction>
      </columnFunction>
      <columnDBFormat>
      </columnDBFormat>
      <columnPK>N</columnPK>
      <columnPermanent>N</columnPermanent>
      <columnComputed>N</columnComputed>
      <columnIdentity>N</columnIdentity>
      <columnReadOnly>N</columnReadOnly>
      <columnRequired>N</columnRequired>
      <columnNotNull>N</columnNotNull>
      <columnCaseSensitive>N</columnCaseSensitive>
      <columnCollation>
      </columnCollation>
      <columnFullText>N</columnFullText>
      <columnVisibleWidth>%ISD_DEFAULT%</columnVisibleWidth>
      <columnTableAliasName>
      </columnTableAliasName>
      <applyLabelText>Y</applyLabelText>
    </Column>
    <Column InternalName="27" Priority="28" ColumnNum="27">
      <columnName>inventory_status_id</columnName>
      <columnUIName>%ISD_DEFAULT%</columnUIName>
      <columnType>Number</columnType>
      <columnDBType>numeric</columnDBType>
      <columnLengthSet>18.0</columnLengthSet>
      <columnDefault>
      </columnDefault>
      <columnDBDefault>
      </columnDBDefault>
      <columnIndex>N</columnIndex>
      <columnUnique>N</columnUnique>
      <columnFunction>
      </columnFunction>
      <columnDBFormat>
      </columnDBFormat>
      <columnPK>N</columnPK>
      <columnPermanent>N</columnPermanent>
      <columnComputed>N</columnComputed>
      <columnIdentity>N</columnIdentity>
      <columnReadOnly>N</columnReadOnly>
      <columnRequired>N</columnRequired>
      <columnNotNull>N</columnNotNull>
      <columnCaseSensitive>N</columnCaseSensitive>
      <columnCollation>
      </columnCollation>
      <columnFullText>N</columnFullText>
      <columnVisibleWidth>%ISD_DEFAULT%</columnVisibleWidth>
      <columnTableAliasName>
      </columnTableAliasName>
      <applyLabelText>Y</applyLabelText>
    </Column>
    <Column InternalName="28" Priority="29" ColumnNum="28">
      <columnName>equipment_inventory_pic1</columnName>
      <columnUIName>%ISD_DEFAULT%</columnUIName>
      <columnType>Image</columnType>
      <columnDBType>image</columnDBType>
      <columnLengthSet>2147483647</columnLengthSet>
      <columnDefault>
      </columnDefault>
      <columnDBDefault>
      </columnDBDefault>
      <columnIndex>N</columnIndex>
      <columnUnique>N</columnUnique>
      <columnFunction>
      </columnFunction>
      <columnDBFormat>
      </columnDBFormat>
      <columnPK>N</columnPK>
      <columnPermanent>N</columnPermanent>
      <columnComputed>N</columnComputed>
      <columnIdentity>N</columnIdentity>
      <columnReadOnly>N</columnReadOnly>
      <columnRequired>N</columnRequired>
      <columnNotNull>N</columnNotNull>
      <columnCaseSensitive>N</columnCaseSensitive>
      <columnCollation>
      </columnCollation>
      <columnFullText>N</columnFullText>
      <columnVisibleWidth>%ISD_DEFAULT%</columnVisibleWidth>
      <columnTableAliasName>
      </columnTableAliasName>
      <applyLabelText>Y</applyLabelText>
    </Column>
    <Column InternalName="29" Priority="30" ColumnNum="29">
      <columnName>equipment_inventory_pic2</columnName>
      <columnUIName>%ISD_DEFAULT%</columnUIName>
      <columnType>Image</columnType>
      <columnDBType>image</columnDBType>
      <columnLengthSet>2147483647</columnLengthSet>
      <columnDefault>
      </columnDefault>
      <columnDBDefault>
      </columnDBDefault>
      <columnIndex>N</columnIndex>
      <columnUnique>N</columnUnique>
      <columnFunction>
      </columnFunction>
      <columnDBFormat>
      </columnDBFormat>
      <columnPK>N</columnPK>
      <columnPermanent>N</columnPermanent>
      <columnComputed>N</columnComputed>
      <columnIdentity>N</columnIdentity>
      <columnReadOnly>N</columnReadOnly>
      <columnRequired>N</columnRequired>
      <columnNotNull>N</columnNotNull>
      <columnCaseSensitive>N</columnCaseSensitive>
      <columnCollation>
      </columnCollation>
      <columnFullText>N</columnFullText>
      <columnVisibleWidth>%ISD_DEFAULT%</columnVisibleWidth>
      <columnTableAliasName>
      </columnTableAliasName>
      <applyLabelText>Y</applyLabelText>
    </Column>
    <Column InternalName="30" Priority="31" ColumnNum="30">
      <columnName>equipment_inventory_pic3</columnName>
      <columnUIName>%ISD_DEFAULT%</columnUIName>
      <columnType>Image</columnType>
      <columnDBType>image</columnDBType>
      <columnLengthSet>2147483647</columnLengthSet>
      <columnDefault>
      </columnDefault>
      <columnDBDefault>
      </columnDBDefault>
      <columnIndex>N</columnIndex>
      <columnUnique>N</columnUnique>
      <columnFunction>
      </columnFunction>
      <columnDBFormat>
      </columnDBFormat>
      <columnPK>N</columnPK>
      <columnPermanent>N</columnPermanent>
      <columnComputed>N</columnComputed>
      <columnIdentity>N</columnIdentity>
      <columnReadOnly>N</columnReadOnly>
      <columnRequired>N</columnRequired>
      <columnNotNull>N</columnNotNull>
      <columnCaseSensitive>N</columnCaseSensitive>
      <columnCollation>
      </columnCollation>
      <columnFullText>N</columnFullText>
      <columnVisibleWidth>%ISD_DEFAULT%</columnVisibleWidth>
      <columnTableAliasName>
      </columnTableAliasName>
      <applyLabelText>Y</applyLabelText>
    </Column>
    <Column InternalName="31" Priority="32" ColumnNum="31">
      <columnName>technician_id</columnName>
      <columnUIName>%ISD_DEFAULT%</columnUIName>
      <columnType>Number</columnType>
      <columnDBType>int</columnDBType>
      <columnLengthSet>10.0</columnLengthSet>
      <columnDefault>
      </columnDefault>
      <columnDBDefault>
      </columnDBDefault>
      <columnIndex>N</columnIndex>
      <columnUnique>N</columnUnique>
      <columnFunction>
      </columnFunction>
      <columnDBFormat>
      </columnDBFormat>
      <columnPK>N</columnPK>
      <columnPermanent>N</columnPermanent>
      <columnComputed>N</columnComputed>
      <columnIdentity>N</columnIdentity>
      <columnReadOnly>N</columnReadOnly>
      <columnRequired>N</columnRequired>
      <columnNotNull>N</columnNotNull>
      <columnCaseSensitive>N</columnCaseSensitive>
      <columnCollation>
      </columnCollation>
      <columnFullText>N</columnFullText>
      <columnVisibleWidth>%ISD_DEFAULT%</columnVisibleWidth>
      <columnTableAliasName>
      </columnTableAliasName>
      <applyLabelText>Y</applyLabelText>
    </Column>
    <Column InternalName="32" Priority="33" ColumnNum="32">
      <columnName>datetime_added</columnName>
      <columnUIName>%ISD_DEFAULT%</columnUIName>
      <columnType>Date</columnType>
      <columnDBType>datetime</columnDBType>
      <columnLengthSet>
      </columnLengthSet>
      <columnDefault>
      </columnDefault>
      <columnDBDefault>
      </columnDBDefault>
      <columnIndex>N</columnIndex>
      <columnUnique>N</columnUnique>
      <columnFunction>notrim</columnFunction>
      <columnFormat>g</columnFormat>
      <columnDBFormat>g</columnDBFormat>
      <columnPK>N</columnPK>
      <columnPermanent>N</columnPermanent>
      <columnComputed>N</columnComputed>
      <columnIdentity>N</columnIdentity>
      <columnReadOnly>N</columnReadOnly>
      <columnRequired>N</columnRequired>
      <columnNotNull>N</columnNotNull>
      <columnCaseSensitive>N</columnCaseSensitive>
      <columnCollation>
      </columnCollation>
      <columnFullText>N</columnFullText>
      <columnVisibleWidth>%ISD_DEFAULT%</columnVisibleWidth>
      <columnTableAliasName>
      </columnTableAliasName>
      <applyLabelText>Y</applyLabelText>
    </Column>
    <Column InternalName="33" Priority="34" ColumnNum="33">
      <columnName>equipment_type_id</columnName>
      <columnUIName>%ISD_DEFAULT%</columnUIName>
      <columnType>Number</columnType>
      <columnDBType>numeric</columnDBType>
      <columnLengthSet>18.0</columnLengthSet>
      <columnDefault>
      </columnDefault>
      <columnDBDefault>
      </columnDBDefault>
      <columnIndex>N</columnIndex>
      <columnUnique>N</columnUnique>
      <columnFunction>
      </columnFunction>
      <columnDBFormat>
      </columnDBFormat>
      <columnPK>N</columnPK>
      <columnPermanent>N</columnPermanent>
      <columnComputed>N</columnComputed>
      <columnIdentity>N</columnIdentity>
      <columnReadOnly>N</columnReadOnly>
      <columnRequired>N</columnRequired>
      <columnNotNull>N</columnNotNull>
      <columnCaseSensitive>N</columnCaseSensitive>
      <columnCollation>
      </columnCollation>
      <columnFullText>N</columnFullText>
      <columnVisibleWidth>%ISD_DEFAULT%</columnVisibleWidth>
      <columnTableAliasName>
      </columnTableAliasName>
      <applyLabelText>Y</applyLabelText>
    </Column>
    <Column InternalName="34" Priority="35" ColumnNum="34">
      <columnName>shipping_cost</columnName>
      <columnUIName>%ISD_DEFAULT%</columnUIName>
      <columnType>Currency</columnType>
      <columnDBType>money</columnDBType>
      <columnLengthSet>19.4</columnLengthSet>
      <columnDefault>
      </columnDefault>
      <columnDBDefault>
      </columnDBDefault>
      <columnIndex>N</columnIndex>
      <columnUnique>N</columnUnique>
      <columnFunction>
      </columnFunction>
      <columnFormat>C</columnFormat>
      <columnDBFormat>C</columnDBFormat>
      <columnPK>N</columnPK>
      <columnPermanent>N</columnPermanent>
      <columnComputed>N</columnComputed>
      <columnIdentity>N</columnIdentity>
      <columnReadOnly>N</columnReadOnly>
      <columnRequired>N</columnRequired>
      <columnNotNull>N</columnNotNull>
      <columnCaseSensitive>N</columnCaseSensitive>
      <columnCollation>
      </columnCollation>
      <columnFullText>N</columnFullText>
      <columnVisibleWidth>%ISD_DEFAULT%</columnVisibleWidth>
      <columnTableAliasName>
      </columnTableAliasName>
      <applyLabelText>Y</applyLabelText>
    </Column>
    <Column InternalName="35" Priority="36" ColumnNum="35">
      <columnName>shipping_invoice</columnName>
      <columnUIName>%ISD_DEFAULT%</columnUIName>
      <columnType>String</columnType>
      <columnDBType>varchar</columnDBType>
      <columnLengthSet>50</columnLengthSet>
      <columnDefault>
      </columnDefault>
      <columnDBDefault>
      </columnDBDefault>
      <columnIndex>N</columnIndex>
      <columnUnique>N</columnUnique>
      <columnFunction>
      </columnFunction>
      <columnDBFormat>
      </columnDBFormat>
      <columnPK>N</columnPK>
      <columnPermanent>N</columnPermanent>
      <columnComputed>N</columnComputed>
      <columnIdentity>N</columnIdentity>
      <columnReadOnly>N</columnReadOnly>
      <columnRequired>N</columnRequired>
      <columnNotNull>N</columnNotNull>
      <columnCaseSensitive Source="Database">N</columnCaseSensitive>
      <columnCollation>SQL_Latin1_General_CP1_CI_AS</columnCollation>
      <columnFullText>N</columnFullText>
      <columnVisibleWidth>%ISD_DEFAULT%</columnVisibleWidth>
      <columnTableAliasName>
      </columnTableAliasName>
      <applyLabelText>Y</applyLabelText>
    </Column>
    <Column InternalName="36" Priority="37" ColumnNum="36">
      <columnName>oem_ein</columnName>
      <columnUIName>%ISD_DEFAULT%</columnUIName>
      <columnType>String</columnType>
      <columnDBType>varchar</columnDBType>
      <columnLengthSet>50</columnLengthSet>
      <columnDefault>
      </columnDefault>
      <columnDBDefault>
      </columnDBDefault>
      <columnIndex>N</columnIndex>
      <columnUnique>N</columnUnique>
      <columnFunction>
      </columnFunction>
      <columnDBFormat>
      </columnDBFormat>
      <columnPK>N</columnPK>
      <columnPermanent>N</columnPermanent>
      <columnComputed>N</columnComputed>
      <columnIdentity>N</columnIdentity>
      <columnReadOnly>N</columnReadOnly>
      <columnRequired>N</columnRequired>
      <columnNotNull>N</columnNotNull>
      <columnCaseSensitive Source="Database">N</columnCaseSensitive>
      <columnCollation>SQL_Latin1_General_CP1_CI_AS</columnCollation>
      <columnFullText>N</columnFullText>
      <columnVisibleWidth>%ISD_DEFAULT%</columnVisibleWidth>
      <columnTableAliasName>
      </columnTableAliasName>
      <applyLabelText>Y</applyLabelText>
    </Column>
    <Column InternalName="37" Priority="38" ColumnNum="37">
      <columnName>wire_fee</columnName>
      <columnUIName>%ISD_DEFAULT%</columnUIName>
      <columnType>Currency</columnType>
      <columnDBType>money</columnDBType>
      <columnLengthSet>19.4</columnLengthSet>
      <columnDefault>
      </columnDefault>
      <columnDBDefault>
      </columnDBDefault>
      <columnIndex>N</columnIndex>
      <columnUnique>N</columnUnique>
      <columnFunction>
      </columnFunction>
      <columnFormat>C</columnFormat>
      <columnDBFormat>C</columnDBFormat>
      <columnPK>N</columnPK>
      <columnPermanent>N</columnPermanent>
      <columnComputed>N</columnComputed>
      <columnIdentity>N</columnIdentity>
      <columnReadOnly>N</columnReadOnly>
      <columnRequired>N</columnRequired>
      <columnNotNull>N</columnNotNull>
      <columnCaseSensitive>N</columnCaseSensitive>
      <columnCollation>
      </columnCollation>
      <columnFullText>N</columnFullText>
      <columnVisibleWidth>%ISD_DEFAULT%</columnVisibleWidth>
      <columnTableAliasName>
      </columnTableAliasName>
      <applyLabelText>Y</applyLabelText>
    </Column>
    <Column InternalName="38" Priority="39" ColumnNum="38">
      <columnName>ebay_fee</columnName>
      <columnUIName>%ISD_DEFAULT%</columnUIName>
      <columnType>Currency</columnType>
      <columnDBType>money</columnDBType>
      <columnLengthSet>19.4</columnLengthSet>
      <columnDefault>
      </columnDefault>
      <columnDBDefault>
      </columnDBDefault>
      <columnIndex>N</columnIndex>
      <columnUnique>N</columnUnique>
      <columnFunction>
      </columnFunction>
      <columnFormat>C</columnFormat>
      <columnDBFormat>C</columnDBFormat>
      <columnPK>N</columnPK>
      <columnPermanent>N</columnPermanent>
      <columnComputed>N</columnComputed>
      <columnIdentity>N</columnIdentity>
      <columnReadOnly>N</columnReadOnly>
      <columnRequired>N</columnRequired>
      <columnNotNull>N</columnNotNull>
      <columnCaseSensitive>N</columnCaseSensitive>
      <columnCollation>
      </columnCollation>
      <columnFullText>N</columnFullText>
      <columnVisibleWidth>%ISD_DEFAULT%</columnVisibleWidth>
      <columnTableAliasName>
      </columnTableAliasName>
      <applyLabelText>Y</applyLabelText>
    </Column>
    <Column InternalName="39" Priority="40" ColumnNum="39">
      <columnName>paypal_fee</columnName>
      <columnUIName>%ISD_DEFAULT%</columnUIName>
      <columnType>Currency</columnType>
      <columnDBType>money</columnDBType>
      <columnLengthSet>19.4</columnLengthSet>
      <columnDefault>
      </columnDefault>
      <columnDBDefault>
      </columnDBDefault>
      <columnIndex>N</columnIndex>
      <columnUnique>N</columnUnique>
      <columnFunction>
      </columnFunction>
      <columnFormat>C</columnFormat>
      <columnDBFormat>C</columnDBFormat>
      <columnPK>N</columnPK>
      <columnPermanent>N</columnPermanent>
      <columnComputed>N</columnComputed>
      <columnIdentity>N</columnIdentity>
      <columnReadOnly>N</columnReadOnly>
      <columnRequired>N</columnRequired>
      <columnNotNull>N</columnNotNull>
      <columnCaseSensitive>N</columnCaseSensitive>
      <columnCollation>
      </columnCollation>
      <columnFullText>N</columnFullText>
      <columnVisibleWidth>%ISD_DEFAULT%</columnVisibleWidth>
      <columnTableAliasName>
      </columnTableAliasName>
      <applyLabelText>Y</applyLabelText>
    </Column>
    <Column InternalName="40" Priority="41" ColumnNum="40">
      <columnName>credit_card_fee</columnName>
      <columnUIName>%ISD_DEFAULT%</columnUIName>
      <columnType>Currency</columnType>
      <columnDBType>money</columnDBType>
      <columnLengthSet>19.4</columnLengthSet>
      <columnDefault>
      </columnDefault>
      <columnDBDefault>
      </columnDBDefault>
      <columnIndex>N</columnIndex>
      <columnUnique>N</columnUnique>
      <columnFunction>
      </columnFunction>
      <columnFormat>C</columnFormat>
      <columnDBFormat>C</columnDBFormat>
      <columnPK>N</columnPK>
      <columnPermanent>N</columnPermanent>
      <columnComputed>N</columnComputed>
      <columnIdentity>N</columnIdentity>
      <columnReadOnly>N</columnReadOnly>
      <columnRequired>N</columnRequired>
      <columnNotNull>N</columnNotNull>
      <columnCaseSensitive>N</columnCaseSensitive>
      <columnCollation>
      </columnCollation>
      <columnFullText>N</columnFullText>
      <columnVisibleWidth>%ISD_DEFAULT%</columnVisibleWidth>
      <columnTableAliasName>
      </columnTableAliasName>
      <applyLabelText>Y</applyLabelText>
    </Column>
    <Column InternalName="41" Priority="42" ColumnNum="41">
      <columnName>equip_inv_ad_cat_id_1</columnName>
      <columnUIName>%ISD_DEFAULT%</columnUIName>
      <columnType>Number</columnType>
      <columnDBType>numeric</columnDBType>
      <columnLengthSet>18.0</columnLengthSet>
      <columnDefault>
      </columnDefault>
      <columnDBDefault>
      </columnDBDefault>
      <columnIndex>N</columnIndex>
      <columnUnique>N</columnUnique>
      <columnFunction>
      </columnFunction>
      <columnDBFormat>
      </columnDBFormat>
      <columnPK>N</columnPK>
      <columnPermanent>N</columnPermanent>
      <columnComputed>N</columnComputed>
      <columnIdentity>N</columnIdentity>
      <columnReadOnly>N</columnReadOnly>
      <columnRequired>N</columnRequired>
      <columnNotNull>N</columnNotNull>
      <columnCaseSensitive>N</columnCaseSensitive>
      <columnCollation>
      </columnCollation>
      <columnFullText>N</columnFullText>
      <columnVisibleWidth>%ISD_DEFAULT%</columnVisibleWidth>
      <columnTableAliasName>
      </columnTableAliasName>
      <applyLabelText>Y</applyLabelText>
    </Column>
    <Column InternalName="42" Priority="43" ColumnNum="42">
      <columnName>equip_inv_ad_cat_id_2</columnName>
      <columnUIName>%ISD_DEFAULT%</columnUIName>
      <columnType>Number</columnType>
      <columnDBType>numeric</columnDBType>
      <columnLengthSet>18.0</columnLengthSet>
      <columnDefault>
      </columnDefault>
      <columnDBDefault>
      </columnDBDefault>
      <columnIndex>N</columnIndex>
      <columnUnique>N</columnUnique>
      <columnFunction>
      </columnFunction>
      <columnDBFormat>
      </columnDBFormat>
      <columnPK>N</columnPK>
      <columnPermanent>N</columnPermanent>
      <columnComputed>N</columnComputed>
      <columnIdentity>N</columnIdentity>
      <columnReadOnly>N</columnReadOnly>
      <columnRequired>N</columnRequired>
      <columnNotNull>N</columnNotNull>
      <columnCaseSensitive>N</columnCaseSensitive>
      <columnCollation>
      </columnCollation>
      <columnFullText>N</columnFullText>
      <columnVisibleWidth>%ISD_DEFAULT%</columnVisibleWidth>
      <columnTableAliasName>
      </columnTableAliasName>
      <applyLabelText>Y</applyLabelText>
    </Column>
    <Column InternalName="43" Priority="44" ColumnNum="43">
      <columnName>equip_inv_ad_cat_id_3</columnName>
      <columnUIName>%ISD_DEFAULT%</columnUIName>
      <columnType>Number</columnType>
      <columnDBType>numeric</columnDBType>
      <columnLengthSet>18.0</columnLengthSet>
      <columnDefault>
      </columnDefault>
      <columnDBDefault>
      </columnDBDefault>
      <columnIndex>N</columnIndex>
      <columnUnique>N</columnUnique>
      <columnFunction>
      </columnFunction>
      <columnDBFormat>
      </columnDBFormat>
      <columnPK>N</columnPK>
      <columnPermanent>N</columnPermanent>
      <columnComputed>N</columnComputed>
      <columnIdentity>N</columnIdentity>
      <columnReadOnly>N</columnReadOnly>
      <columnRequired>N</columnRequired>
      <columnNotNull>N</columnNotNull>
      <columnCaseSensitive>N</columnCaseSensitive>
      <columnCollation>
      </columnCollation>
      <columnFullText>N</columnFullText>
      <columnVisibleWidth>%ISD_DEFAULT%</columnVisibleWidth>
      <columnTableAliasName>
      </columnTableAliasName>
      <applyLabelText>Y</applyLabelText>
    </Column>
    <Column InternalName="44" Priority="45" ColumnNum="44">
      <columnName>shipping_tracking</columnName>
      <columnUIName>%ISD_DEFAULT%</columnUIName>
      <columnType>String</columnType>
      <columnDBType>varchar</columnDBType>
      <columnLengthSet>50</columnLengthSet>
      <columnDefault>
      </columnDefault>
      <columnDBDefault>
      </columnDBDefault>
      <columnIndex>N</columnIndex>
      <columnUnique>N</columnUnique>
      <columnFunction>
      </columnFunction>
      <columnDBFormat>
      </columnDBFormat>
      <columnPK>N</columnPK>
      <columnPermanent>N</columnPermanent>
      <columnComputed>N</columnComputed>
      <columnIdentity>N</columnIdentity>
      <columnReadOnly>N</columnReadOnly>
      <columnRequired>N</columnRequired>
      <columnNotNull>N</columnNotNull>
      <columnCaseSensitive Source="Database">N</columnCaseSensitive>
      <columnCollation>SQL_Latin1_General_CP1_CI_AS</columnCollation>
      <columnFullText>N</columnFullText>
      <columnVisibleWidth>%ISD_DEFAULT%</columnVisibleWidth>
      <columnTableAliasName>
      </columnTableAliasName>
      <applyLabelText>Y</applyLabelText>
    </Column>
    <Column InternalName="45" Priority="46" ColumnNum="45">
      <columnName>other_fee</columnName>
      <columnUIName>%ISD_DEFAULT%</columnUIName>
      <columnType>Currency</columnType>
      <columnDBType>money</columnDBType>
      <columnLengthSet>19.4</columnLengthSet>
      <columnDefault>
      </columnDefault>
      <columnDBDefault>
      </columnDBDefault>
      <columnIndex>N</columnIndex>
      <columnUnique>N</columnUnique>
      <columnFunction>
      </columnFunction>
      <columnFormat>C</columnFormat>
      <columnDBFormat>C</columnDBFormat>
      <columnPK>N</columnPK>
      <columnPermanent>N</columnPermanent>
      <columnComputed>N</columnComputed>
      <columnIdentity>N</columnIdentity>
      <columnReadOnly>N</columnReadOnly>
      <columnRequired>N</columnRequired>
      <columnNotNull>N</columnNotNull>
      <columnCaseSensitive>N</columnCaseSensitive>
      <columnCollation>
      </columnCollation>
      <columnFullText>N</columnFullText>
      <columnVisibleWidth>%ISD_DEFAULT%</columnVisibleWidth>
      <columnTableAliasName>
      </columnTableAliasName>
      <applyLabelText>Y</applyLabelText>
    </Column>
    <Column InternalName="46" Priority="47" ColumnNum="46">
      <columnName>shipping_retail</columnName>
      <columnUIName>%ISD_DEFAULT%</columnUIName>
      <columnType>Currency</columnType>
      <columnDBType>money</columnDBType>
      <columnLengthSet>19.4</columnLengthSet>
      <columnDefault>
      </columnDefault>
      <columnDBDefault>
      </columnDBDefault>
      <columnIndex>N</columnIndex>
      <columnUnique>N</columnUnique>
      <columnFunction>
      </columnFunction>
      <columnFormat>C</columnFormat>
      <columnDBFormat>C</columnDBFormat>
      <columnPK>N</columnPK>
      <columnPermanent>N</columnPermanent>
      <columnComputed>N</columnComputed>
      <columnIdentity>N</columnIdentity>
      <columnReadOnly>N</columnReadOnly>
      <columnRequired>N</columnRequired>
      <columnNotNull>N</columnNotNull>
      <columnCaseSensitive>N</columnCaseSensitive>
      <columnCollation>
      </columnCollation>
      <columnFullText>N</columnFullText>
      <columnVisibleWidth>%ISD_DEFAULT%</columnVisibleWidth>
      <columnTableAliasName>
      </columnTableAliasName>
      <applyLabelText>Y</applyLabelText>
    </Column>
    <Column InternalName="47" Priority="48" ColumnNum="47">
      <columnName>shipvia</columnName>
      <columnUIName>%ISD_DEFAULT%</columnUIName>
      <columnType>String</columnType>
      <columnDBType>nvarchar</columnDBType>
      <columnLengthSet>20</columnLengthSet>
      <columnDefault>
      </columnDefault>
      <columnDBDefault>
      </columnDBDefault>
      <columnIndex>N</columnIndex>
      <columnUnique>N</columnUnique>
      <columnFunction>
      </columnFunction>
      <columnDBFormat>
      </columnDBFormat>
      <columnPK>N</columnPK>
      <columnPermanent>N</columnPermanent>
      <columnComputed>N</columnComputed>
      <columnIdentity>N</columnIdentity>
      <columnReadOnly>N</columnReadOnly>
      <columnRequired>N</columnRequired>
      <columnNotNull>N</columnNotNull>
      <columnCaseSensitive Source="Database">N</columnCaseSensitive>
      <columnCollation>SQL_Latin1_General_CP1_CI_AS</columnCollation>
      <columnFullText>N</columnFullText>
      <columnVisibleWidth>%ISD_DEFAULT%</columnVisibleWidth>
      <columnTableAliasName>
      </columnTableAliasName>
      <applyLabelText>Y</applyLabelText>
    </Column>
    <Column InternalName="48" Priority="49" ColumnNum="48">
      <columnName>shipping_date</columnName>
      <columnUIName>%ISD_DEFAULT%</columnUIName>
      <columnType>Date</columnType>
      <columnDBType>date</columnDBType>
      <columnLengthSet>
      </columnLengthSet>
      <columnDefault>
      </columnDefault>
      <columnDBDefault>
      </columnDBDefault>
      <columnIndex>N</columnIndex>
      <columnUnique>N</columnUnique>
      <columnFunction>notrim</columnFunction>
      <columnFormat>d</columnFormat>
      <columnDBFormat>d</columnDBFormat>
      <columnPK>N</columnPK>
      <columnPermanent>N</columnPermanent>
      <columnComputed>N</columnComputed>
      <columnIdentity>N</columnIdentity>
      <columnReadOnly>N</columnReadOnly>
      <columnRequired>N</columnRequired>
      <columnNotNull>N</columnNotNull>
      <columnCaseSensitive>N</columnCaseSensitive>
      <columnCollation>
      </columnCollation>
      <columnFullText>N</columnFullText>
      <columnVisibleWidth>%ISD_DEFAULT%</columnVisibleWidth>
      <columnTableAliasName>
      </columnTableAliasName>
      <applyLabelText>Y</applyLabelText>
    </Column>
    <Column InternalName="49" Priority="50" ColumnNum="49">
      <columnName>customer_purchased</columnName>
      <columnUIName>%ISD_DEFAULT%</columnUIName>
      <columnType>Number</columnType>
      <columnDBType>int</columnDBType>
      <columnLengthSet>10.0</columnLengthSet>
      <columnDefault>
      </columnDefault>
      <columnDBDefault>
      </columnDBDefault>
      <columnIndex>N</columnIndex>
      <columnUnique>N</columnUnique>
      <columnFunction>
      </columnFunction>
      <columnDBFormat>
      </columnDBFormat>
      <columnPK>N</columnPK>
      <columnPermanent>N</columnPermanent>
      <columnComputed>N</columnComputed>
      <columnIdentity>N</columnIdentity>
      <columnReadOnly>N</columnReadOnly>
      <columnRequired>N</columnRequired>
      <columnNotNull>N</columnNotNull>
      <columnCaseSensitive>N</columnCaseSensitive>
      <columnCollation>
      </columnCollation>
      <columnFullText>N</columnFullText>
      <columnVisibleWidth>%ISD_DEFAULT%</columnVisibleWidth>
      <columnTableAliasName>
      </columnTableAliasName>
      <applyLabelText>Y</applyLabelText>
    </Column>
    <Column InternalName="50" Priority="51" ColumnNum="50">
      <columnName>vendno</columnName>
      <columnUIName>%ISD_DEFAULT%</columnUIName>
      <columnType>Number</columnType>
      <columnDBType>int</columnDBType>
      <columnLengthSet>10.0</columnLengthSet>
      <columnDefault>
      </columnDefault>
      <columnDBDefault>
      </columnDBDefault>
      <columnIndex>N</columnIndex>
      <columnUnique>N</columnUnique>
      <columnFunction>
      </columnFunction>
      <columnDBFormat>
      </columnDBFormat>
      <columnPK>N</columnPK>
      <columnPermanent>N</columnPermanent>
      <columnComputed>N</columnComputed>
      <columnIdentity>N</columnIdentity>
      <columnReadOnly>N</columnReadOnly>
      <columnRequired>N</columnRequired>
      <columnNotNull>N</columnNotNull>
      <columnCaseSensitive>N</columnCaseSensitive>
      <columnCollation>
      </columnCollation>
      <columnFullText>N</columnFullText>
      <columnVisibleWidth>%ISD_DEFAULT%</columnVisibleWidth>
      <columnTableAliasName>
      </columnTableAliasName>
      <applyLabelText>Y</applyLabelText>
    </Column>
    <Column InternalName="51" Priority="52" ColumnNum="51">
      <columnName>equipment_inventory_batch_details_id</columnName>
      <columnUIName>%ISD_DEFAULT%</columnUIName>
      <columnType>Number</columnType>
      <columnDBType>numeric</columnDBType>
      <columnLengthSet>18.0</columnLengthSet>
      <columnDefault>
      </columnDefault>
      <columnDBDefault>
      </columnDBDefault>
      <columnIndex>N</columnIndex>
      <columnUnique>N</columnUnique>
      <columnFunction>
      </columnFunction>
      <columnDBFormat>
      </columnDBFormat>
      <columnPK>N</columnPK>
      <columnPermanent>N</columnPermanent>
      <columnComputed>N</columnComputed>
      <columnIdentity>N</columnIdentity>
      <columnReadOnly>N</columnReadOnly>
      <columnRequired>N</columnRequired>
      <columnNotNull>N</columnNotNull>
      <columnCaseSensitive>N</columnCaseSensitive>
      <columnCollation>
      </columnCollation>
      <columnFullText>N</columnFullText>
      <columnVisibleWidth>%ISD_DEFAULT%</columnVisibleWidth>
      <columnTableAliasName>
      </columnTableAliasName>
      <applyLabelText>Y</applyLabelText>
    </Column>
    <Column InternalName="52" Priority="53" ColumnNum="52">
      <columnName>equipment_inventory_batch_id</columnName>
      <columnUIName>%ISD_DEFAULT%</columnUIName>
      <columnType>Number</columnType>
      <columnDBType>numeric</columnDBType>
      <columnLengthSet>18.0</columnLengthSet>
      <columnDefault>
      </columnDefault>
      <columnDBDefault>
      </columnDBDefault>
      <columnIndex>N</columnIndex>
      <columnUnique>N</columnUnique>
      <columnFunction>
      </columnFunction>
      <columnDBFormat>
      </columnDBFormat>
      <columnPK>N</columnPK>
      <columnPermanent>N</columnPermanent>
      <columnComputed>N</columnComputed>
      <columnIdentity>N</columnIdentity>
      <columnReadOnly>N</columnReadOnly>
      <columnRequired>N</columnRequired>
      <columnNotNull>N</columnNotNull>
      <columnCaseSensitive>N</columnCaseSensitive>
      <columnCollation>
      </columnCollation>
      <columnFullText>N</columnFullText>
      <columnVisibleWidth>%ISD_DEFAULT%</columnVisibleWidth>
      <columnTableAliasName>
      </columnTableAliasName>
      <applyLabelText>Y</applyLabelText>
    </Column>
    <Column InternalName="53" Priority="54" ColumnNum="53">
      <columnName>new_category_id</columnName>
      <columnUIName>%ISD_DEFAULT%</columnUIName>
      <columnType>Number</columnType>
      <columnDBType>numeric</columnDBType>
      <columnLengthSet>18.0</columnLengthSet>
      <columnDefault>
      </columnDefault>
      <columnDBDefault>
      </columnDBDefault>
      <columnIndex>N</columnIndex>
      <columnUnique>N</columnUnique>
      <columnFunction>
      </columnFunction>
      <columnDBFormat>
      </columnDBFormat>
      <columnPK>N</columnPK>
      <columnPermanent>N</columnPermanent>
      <columnComputed>N</columnComputed>
      <columnIdentity>N</columnIdentity>
      <columnReadOnly>N</columnReadOnly>
      <columnRequired>N</columnRequired>
      <columnNotNull>N</columnNotNull>
      <columnCaseSensitive>N</columnCaseSensitive>
      <columnCollation>
      </columnCollation>
      <columnFullText>N</columnFullText>
      <columnVisibleWidth>%ISD_DEFAULT%</columnVisibleWidth>
      <columnTableAliasName>
      </columnTableAliasName>
      <applyLabelText>Y</applyLabelText>
    </Column>
    <Column InternalName="54" Priority="55" ColumnNum="54">
      <columnName>equipment_inventory_pic4</columnName>
      <columnUIName>%ISD_DEFAULT%</columnUIName>
      <columnType>Image</columnType>
      <columnDBType>image</columnDBType>
      <columnLengthSet>2147483647</columnLengthSet>
      <columnDefault>
      </columnDefault>
      <columnDBDefault>
      </columnDBDefault>
      <columnIndex>N</columnIndex>
      <columnUnique>N</columnUnique>
      <columnFunction>
      </columnFunction>
      <columnDBFormat>
      </columnDBFormat>
      <columnPK>N</columnPK>
      <columnPermanent>N</columnPermanent>
      <columnComputed>N</columnComputed>
      <columnIdentity>N</columnIdentity>
      <columnReadOnly>N</columnReadOnly>
      <columnRequired>N</columnRequired>
      <columnNotNull>N</columnNotNull>
      <columnCaseSensitive>N</columnCaseSensitive>
      <columnCollation>
      </columnCollation>
      <columnFullText>N</columnFullText>
      <columnVisibleWidth>%ISD_DEFAULT%</columnVisibleWidth>
      <columnTableAliasName>
      </columnTableAliasName>
      <applyLabelText>Y</applyLabelText>
    </Column>
    <Column InternalName="55" Priority="56" ColumnNum="55">
      <columnName>equipment_inventory_pic5</columnName>
      <columnUIName>%ISD_DEFAULT%</columnUIName>
      <columnType>Image</columnType>
      <columnDBType>image</columnDBType>
      <columnLengthSet>2147483647</columnLengthSet>
      <columnDefault>
      </columnDefault>
      <columnDBDefault>
      </columnDBDefault>
      <columnIndex>N</columnIndex>
      <columnUnique>N</columnUnique>
      <columnFunction>
      </columnFunction>
      <columnDBFormat>
      </columnDBFormat>
      <columnPK>N</columnPK>
      <columnPermanent>N</columnPermanent>
      <columnComputed>N</columnComputed>
      <columnIdentity>N</columnIdentity>
      <columnReadOnly>N</columnReadOnly>
      <columnRequired>N</columnRequired>
      <columnNotNull>N</columnNotNull>
      <columnCaseSensitive>N</columnCaseSensitive>
      <columnCollation>
      </columnCollation>
      <columnFullText>N</columnFullText>
      <columnVisibleWidth>%ISD_DEFAULT%</columnVisibleWidth>
      <columnTableAliasName>
      </columnTableAliasName>
      <applyLabelText>Y</applyLabelText>
    </Column>
    <Column InternalName="56" Priority="57" ColumnNum="56">
      <columnName>equipment_inventory_pic6</columnName>
      <columnUIName>%ISD_DEFAULT%</columnUIName>
      <columnType>Image</columnType>
      <columnDBType>image</columnDBType>
      <columnLengthSet>2147483647</columnLengthSet>
      <columnDefault>
      </columnDefault>
      <columnDBDefault>
      </columnDBDefault>
      <columnIndex>N</columnIndex>
      <columnUnique>N</columnUnique>
      <columnFunction>
      </columnFunction>
      <columnDBFormat>
      </columnDBFormat>
      <columnPK>N</columnPK>
      <columnPermanent>N</columnPermanent>
      <columnComputed>N</columnComputed>
      <columnIdentity>N</columnIdentity>
      <columnReadOnly>N</columnReadOnly>
      <columnRequired>N</columnRequired>
      <columnNotNull>N</columnNotNull>
      <columnCaseSensitive>N</columnCaseSensitive>
      <columnCollation>
      </columnCollation>
      <columnFullText>N</columnFullText>
      <columnVisibleWidth>%ISD_DEFAULT%</columnVisibleWidth>
      <columnTableAliasName>
      </columnTableAliasName>
      <applyLabelText>Y</applyLabelText>
    </Column>
    <Column InternalName="57" Priority="58" ColumnNum="57">
      <columnName>equipment_inventory_pic7</columnName>
      <columnUIName>%ISD_DEFAULT%</columnUIName>
      <columnType>Image</columnType>
      <columnDBType>image</columnDBType>
      <columnLengthSet>2147483647</columnLengthSet>
      <columnDefault>
      </columnDefault>
      <columnDBDefault>
      </columnDBDefault>
      <columnIndex>N</columnIndex>
      <columnUnique>N</columnUnique>
      <columnFunction>
      </columnFunction>
      <columnDBFormat>
      </columnDBFormat>
      <columnPK>N</columnPK>
      <columnPermanent>N</columnPermanent>
      <columnComputed>N</columnComputed>
      <columnIdentity>N</columnIdentity>
      <columnReadOnly>N</columnReadOnly>
      <columnRequired>N</columnRequired>
      <columnNotNull>N</columnNotNull>
      <columnCaseSensitive>N</columnCaseSensitive>
      <columnCollation>
      </columnCollation>
      <columnFullText>N</columnFullText>
      <columnVisibleWidth>%ISD_DEFAULT%</columnVisibleWidth>
      <columnTableAliasName>
      </columnTableAliasName>
      <applyLabelText>Y</applyLabelText>
    </Column>
    <Column InternalName="58" Priority="59" ColumnNum="58">
      <columnName>equipment_inventory_pic8</columnName>
      <columnUIName>%ISD_DEFAULT%</columnUIName>
      <columnType>Image</columnType>
      <columnDBType>image</columnDBType>
      <columnLengthSet>2147483647</columnLengthSet>
      <columnDefault>
      </columnDefault>
      <columnDBDefault>
      </columnDBDefault>
      <columnIndex>N</columnIndex>
      <columnUnique>N</columnUnique>
      <columnFunction>
      </columnFunction>
      <columnDBFormat>
      </columnDBFormat>
      <columnPK>N</columnPK>
      <columnPermanent>N</columnPermanent>
      <columnComputed>N</columnComputed>
      <columnIdentity>N</columnIdentity>
      <columnReadOnly>N</columnReadOnly>
      <columnRequired>N</columnRequired>
      <columnNotNull>N</columnNotNull>
      <columnCaseSensitive>N</columnCaseSensitive>
      <columnCollation>
      </columnCollation>
      <columnFullText>N</columnFullText>
      <columnVisibleWidth>%ISD_DEFAULT%</columnVisibleWidth>
      <columnTableAliasName>
      </columnTableAliasName>
      <applyLabelText>Y</applyLabelText>
    </Column>
    <Column InternalName="59" Priority="60" ColumnNum="59">
      <columnName>equipment_inventory_pic9</columnName>
      <columnUIName>%ISD_DEFAULT%</columnUIName>
      <columnType>Image</columnType>
      <columnDBType>image</columnDBType>
      <columnLengthSet>2147483647</columnLengthSet>
      <columnDefault>
      </columnDefault>
      <columnDBDefault>
      </columnDBDefault>
      <columnIndex>N</columnIndex>
      <columnUnique>N</columnUnique>
      <columnFunction>
      </columnFunction>
      <columnDBFormat>
      </columnDBFormat>
      <columnPK>N</columnPK>
      <columnPermanent>N</columnPermanent>
      <columnComputed>N</columnComputed>
      <columnIdentity>N</columnIdentity>
      <columnReadOnly>N</columnReadOnly>
      <columnRequired>N</columnRequired>
      <columnNotNull>N</columnNotNull>
      <columnCaseSensitive>N</columnCaseSensitive>
      <columnCollation>
      </columnCollation>
      <columnFullText>N</columnFullText>
      <columnVisibleWidth>%ISD_DEFAULT%</columnVisibleWidth>
      <columnTableAliasName>
      </columnTableAliasName>
      <applyLabelText>Y</applyLabelText>
    </Column>
    <Column InternalName="60" Priority="61" ColumnNum="60">
      <columnName>equipment_inventory_pic10</columnName>
      <columnUIName>%ISD_DEFAULT%</columnUIName>
      <columnType>Image</columnType>
      <columnDBType>image</columnDBType>
      <columnLengthSet>2147483647</columnLengthSet>
      <columnDefault>
      </columnDefault>
      <columnDBDefault>
      </columnDBDefault>
      <columnIndex>N</columnIndex>
      <columnUnique>N</columnUnique>
      <columnFunction>
      </columnFunction>
      <columnDBFormat>
      </columnDBFormat>
      <columnPK>N</columnPK>
      <columnPermanent>N</columnPermanent>
      <columnComputed>N</columnComputed>
      <columnIdentity>N</columnIdentity>
      <columnReadOnly>N</columnReadOnly>
      <columnRequired>N</columnRequired>
      <columnNotNull>N</columnNotNull>
      <columnCaseSensitive>N</columnCaseSensitive>
      <columnCollation>
      </columnCollation>
      <columnFullText>N</columnFullText>
      <columnVisibleWidth>%ISD_DEFAULT%</columnVisibleWidth>
      <columnTableAliasName>
      </columnTableAliasName>
      <applyLabelText>Y</applyLabelText>
    </Column>
    <Column InternalName="61" Priority="62" ColumnNum="61">
      <columnName>sold_by</columnName>
      <columnUIName>%ISD_DEFAULT%</columnUIName>
      <columnType>Number</columnType>
      <columnDBType>int</columnDBType>
      <columnLengthSet>10.0</columnLengthSet>
      <columnDefault>
      </columnDefault>
      <columnDBDefault>
      </columnDBDefault>
      <columnIndex>N</columnIndex>
      <columnUnique>N</columnUnique>
      <columnFunction>
      </columnFunction>
      <columnDBFormat>
      </columnDBFormat>
      <columnPK>N</columnPK>
      <columnPermanent>N</columnPermanent>
      <columnComputed>N</columnComputed>
      <columnIdentity>N</columnIdentity>
      <columnReadOnly>N</columnReadOnly>
      <columnRequired>N</columnRequired>
      <columnNotNull>N</columnNotNull>
      <columnCaseSensitive>N</columnCaseSensitive>
      <columnCollation>
      </columnCollation>
      <columnFullText>N</columnFullText>
      <columnVisibleWidth>%ISD_DEFAULT%</columnVisibleWidth>
      <columnTableAliasName>
      </columnTableAliasName>
      <applyLabelText>Y</applyLabelText>
    </Column>
    <Column InternalName="62" Priority="63" ColumnNum="62">
      <columnName>equipment_qty</columnName>
      <columnUIName>%ISD_DEFAULT%</columnUIName>
      <columnType>Number</columnType>
      <columnDBType>int</columnDBType>
      <columnLengthSet>10.0</columnLengthSet>
      <columnDefault>
      </columnDefault>
      <columnDBDefault>
      </columnDBDefault>
      <columnIndex>N</columnIndex>
      <columnUnique>N</columnUnique>
      <columnFunction>
      </columnFunction>
      <columnDBFormat>
      </columnDBFormat>
      <columnPK>N</columnPK>
      <columnPermanent>N</columnPermanent>
      <columnComputed>N</columnComputed>
      <columnIdentity>N</columnIdentity>
      <columnReadOnly>N</columnReadOnly>
      <columnRequired>N</columnRequired>
      <columnNotNull>N</columnNotNull>
      <columnCaseSensitive>N</columnCaseSensitive>
      <columnCollation>
      </columnCollation>
      <columnFullText>N</columnFullText>
      <columnVisibleWidth>%ISD_DEFAULT%</columnVisibleWidth>
      <columnTableAliasName>
      </columnTableAliasName>
      <applyLabelText>Y</applyLabelText>
    </Column>
    <Column InternalName="63" Priority="64" ColumnNum="63">
      <columnName>equipment_inventory_pic1_name</columnName>
      <columnUIName>%ISD_DEFAULT%</columnUIName>
      <columnType>String</columnType>
      <columnDBType>varchar</columnDBType>
      <columnLengthSet>50</columnLengthSet>
      <columnDefault>
      </columnDefault>
      <columnDBDefault>
      </columnDBDefault>
      <columnIndex>N</columnIndex>
      <columnUnique>N</columnUnique>
      <columnFunction>
      </columnFunction>
      <columnDBFormat>
      </columnDBFormat>
      <columnPK>N</columnPK>
      <columnPermanent>N</columnPermanent>
      <columnComputed>N</columnComputed>
      <columnIdentity>N</columnIdentity>
      <columnReadOnly>N</columnReadOnly>
      <columnRequired>N</columnRequired>
      <columnNotNull>N</columnNotNull>
      <columnCaseSensitive Source="Database">N</columnCaseSensitive>
      <columnCollation>SQL_Latin1_General_CP1_CI_AS</columnCollation>
      <columnFullText>N</columnFullText>
      <columnVisibleWidth>%ISD_DEFAULT%</columnVisibleWidth>
      <columnTableAliasName>
      </columnTableAliasName>
      <applyLabelText>Y</applyLabelText>
    </Column>
    <Column InternalName="64" Priority="65" ColumnNum="64">
      <columnName>equipment_inventory_pic2_name</columnName>
      <columnUIName>%ISD_DEFAULT%</columnUIName>
      <columnType>String</columnType>
      <columnDBType>varchar</columnDBType>
      <columnLengthSet>50</columnLengthSet>
      <columnDefault>
      </columnDefault>
      <columnDBDefault>
      </columnDBDefault>
      <columnIndex>N</columnIndex>
      <columnUnique>N</columnUnique>
      <columnFunction>
      </columnFunction>
      <columnDBFormat>
      </columnDBFormat>
      <columnPK>N</columnPK>
      <columnPermanent>N</columnPermanent>
      <columnComputed>N</columnComputed>
      <columnIdentity>N</columnIdentity>
      <columnReadOnly>N</columnReadOnly>
      <columnRequired>N</columnRequired>
      <columnNotNull>N</columnNotNull>
      <columnCaseSensitive Source="Database">N</columnCaseSensitive>
      <columnCollation>SQL_Latin1_General_CP1_CI_AS</columnCollation>
      <columnFullText>N</columnFullText>
      <columnVisibleWidth>%ISD_DEFAULT%</columnVisibleWidth>
      <columnTableAliasName>
      </columnTableAliasName>
      <applyLabelText>Y</applyLabelText>
    </Column>
    <Column InternalName="65" Priority="66" ColumnNum="65">
      <columnName>equipment_inventory_pic3_name</columnName>
      <columnUIName>%ISD_DEFAULT%</columnUIName>
      <columnType>String</columnType>
      <columnDBType>varchar</columnDBType>
      <columnLengthSet>50</columnLengthSet>
      <columnDefault>
      </columnDefault>
      <columnDBDefault>
      </columnDBDefault>
      <columnIndex>N</columnIndex>
      <columnUnique>N</columnUnique>
      <columnFunction>
      </columnFunction>
      <columnDBFormat>
      </columnDBFormat>
      <columnPK>N</columnPK>
      <columnPermanent>N</columnPermanent>
      <columnComputed>N</columnComputed>
      <columnIdentity>N</columnIdentity>
      <columnReadOnly>N</columnReadOnly>
      <columnRequired>N</columnRequired>
      <columnNotNull>N</columnNotNull>
      <columnCaseSensitive Source="Database">N</columnCaseSensitive>
      <columnCollation>SQL_Latin1_General_CP1_CI_AS</columnCollation>
      <columnFullText>N</columnFullText>
      <columnVisibleWidth>%ISD_DEFAULT%</columnVisibleWidth>
      <columnTableAliasName>
      </columnTableAliasName>
      <applyLabelText>Y</applyLabelText>
    </Column>
    <Column InternalName="66" Priority="67" ColumnNum="66">
      <columnName>equipment_inventory_pic4_name</columnName>
      <columnUIName>%ISD_DEFAULT%</columnUIName>
      <columnType>String</columnType>
      <columnDBType>varchar</columnDBType>
      <columnLengthSet>50</columnLengthSet>
      <columnDefault>
      </columnDefault>
      <columnDBDefault>
      </columnDBDefault>
      <columnIndex>N</columnIndex>
      <columnUnique>N</columnUnique>
      <columnFunction>
      </columnFunction>
      <columnDBFormat>
      </columnDBFormat>
      <columnPK>N</columnPK>
      <columnPermanent>N</columnPermanent>
      <columnComputed>N</columnComputed>
      <columnIdentity>N</columnIdentity>
      <columnReadOnly>N</columnReadOnly>
      <columnRequired>N</columnRequired>
      <columnNotNull>N</columnNotNull>
      <columnCaseSensitive Source="Database">N</columnCaseSensitive>
      <columnCollation>SQL_Latin1_General_CP1_CI_AS</columnCollation>
      <columnFullText>N</columnFullText>
      <columnVisibleWidth>%ISD_DEFAULT%</columnVisibleWidth>
      <columnTableAliasName>
      </columnTableAliasName>
      <applyLabelText>Y</applyLabelText>
    </Column>
    <Column InternalName="67" Priority="68" ColumnNum="67">
      <columnName>equipment_inventory_pic5_name</columnName>
      <columnUIName>%ISD_DEFAULT%</columnUIName>
      <columnType>String</columnType>
      <columnDBType>varchar</columnDBType>
      <columnLengthSet>50</columnLengthSet>
      <columnDefault>
      </columnDefault>
      <columnDBDefault>
      </columnDBDefault>
      <columnIndex>N</columnIndex>
      <columnUnique>N</columnUnique>
      <columnFunction>
      </columnFunction>
      <columnDBFormat>
      </columnDBFormat>
      <columnPK>N</columnPK>
      <columnPermanent>N</columnPermanent>
      <columnComputed>N</columnComputed>
      <columnIdentity>N</columnIdentity>
      <columnReadOnly>N</columnReadOnly>
      <columnRequired>N</columnRequired>
      <columnNotNull>N</columnNotNull>
      <columnCaseSensitive Source="Database">N</columnCaseSensitive>
      <columnCollation>SQL_Latin1_General_CP1_CI_AS</columnCollation>
      <columnFullText>N</columnFullText>
      <columnVisibleWidth>%ISD_DEFAULT%</columnVisibleWidth>
      <columnTableAliasName>
      </columnTableAliasName>
      <applyLabelText>Y</applyLabelText>
    </Column>
    <Column InternalName="68" Priority="69" ColumnNum="68">
      <columnName>equipment_inventory_pic6_name</columnName>
      <columnUIName>%ISD_DEFAULT%</columnUIName>
      <columnType>String</columnType>
      <columnDBType>varchar</columnDBType>
      <columnLengthSet>50</columnLengthSet>
      <columnDefault>
      </columnDefault>
      <columnDBDefault>
      </columnDBDefault>
      <columnIndex>N</columnIndex>
      <columnUnique>N</columnUnique>
      <columnFunction>
      </columnFunction>
      <columnDBFormat>
      </columnDBFormat>
      <columnPK>N</columnPK>
      <columnPermanent>N</columnPermanent>
      <columnComputed>N</columnComputed>
      <columnIdentity>N</columnIdentity>
      <columnReadOnly>N</columnReadOnly>
      <columnRequired>N</columnRequired>
      <columnNotNull>N</columnNotNull>
      <columnCaseSensitive Source="Database">N</columnCaseSensitive>
      <columnCollation>SQL_Latin1_General_CP1_CI_AS</columnCollation>
      <columnFullText>N</columnFullText>
      <columnVisibleWidth>%ISD_DEFAULT%</columnVisibleWidth>
      <columnTableAliasName>
      </columnTableAliasName>
      <applyLabelText>Y</applyLabelText>
    </Column>
    <Column InternalName="69" Priority="70" ColumnNum="69">
      <columnName>equipment_inventory_pic7_name</columnName>
      <columnUIName>%ISD_DEFAULT%</columnUIName>
      <columnType>String</columnType>
      <columnDBType>varchar</columnDBType>
      <columnLengthSet>50</columnLengthSet>
      <columnDefault>
      </columnDefault>
      <columnDBDefault>
      </columnDBDefault>
      <columnIndex>N</columnIndex>
      <columnUnique>N</columnUnique>
      <columnFunction>
      </columnFunction>
      <columnDBFormat>
      </columnDBFormat>
      <columnPK>N</columnPK>
      <columnPermanent>N</columnPermanent>
      <columnComputed>N</columnComputed>
      <columnIdentity>N</columnIdentity>
      <columnReadOnly>N</columnReadOnly>
      <columnRequired>N</columnRequired>
      <columnNotNull>N</columnNotNull>
      <columnCaseSensitive Source="Database">N</columnCaseSensitive>
      <columnCollation>SQL_Latin1_General_CP1_CI_AS</columnCollation>
      <columnFullText>N</columnFullText>
      <columnVisibleWidth>%ISD_DEFAULT%</columnVisibleWidth>
      <columnTableAliasName>
      </columnTableAliasName>
      <applyLabelText>Y</applyLabelText>
    </Column>
    <Column InternalName="70" Priority="71" ColumnNum="70">
      <columnName>equipment_inventory_pic8_name</columnName>
      <columnUIName>%ISD_DEFAULT%</columnUIName>
      <columnType>String</columnType>
      <columnDBType>varchar</columnDBType>
      <columnLengthSet>50</columnLengthSet>
      <columnDefault>
      </columnDefault>
      <columnDBDefault>
      </columnDBDefault>
      <columnIndex>N</columnIndex>
      <columnUnique>N</columnUnique>
      <columnFunction>
      </columnFunction>
      <columnDBFormat>
      </columnDBFormat>
      <columnPK>N</columnPK>
      <columnPermanent>N</columnPermanent>
      <columnComputed>N</columnComputed>
      <columnIdentity>N</columnIdentity>
      <columnReadOnly>N</columnReadOnly>
      <columnRequired>N</columnRequired>
      <columnNotNull>N</columnNotNull>
      <columnCaseSensitive Source="Database">N</columnCaseSensitive>
      <columnCollation>SQL_Latin1_General_CP1_CI_AS</columnCollation>
      <columnFullText>N</columnFullText>
      <columnVisibleWidth>%ISD_DEFAULT%</columnVisibleWidth>
      <columnTableAliasName>
      </columnTableAliasName>
      <applyLabelText>Y</applyLabelText>
    </Column>
    <Column InternalName="71" Priority="72" ColumnNum="71">
      <columnName>equipment_inventory_pic9_name</columnName>
      <columnUIName>%ISD_DEFAULT%</columnUIName>
      <columnType>String</columnType>
      <columnDBType>varchar</columnDBType>
      <columnLengthSet>50</columnLengthSet>
      <columnDefault>
      </columnDefault>
      <columnDBDefault>
      </columnDBDefault>
      <columnIndex>N</columnIndex>
      <columnUnique>N</columnUnique>
      <columnFunction>
      </columnFunction>
      <columnDBFormat>
      </columnDBFormat>
      <columnPK>N</columnPK>
      <columnPermanent>N</columnPermanent>
      <columnComputed>N</columnComputed>
      <columnIdentity>N</columnIdentity>
      <columnReadOnly>N</columnReadOnly>
      <columnRequired>N</columnRequired>
      <columnNotNull>N</columnNotNull>
      <columnCaseSensitive Source="Database">N</columnCaseSensitive>
      <columnCollation>SQL_Latin1_General_CP1_CI_AS</columnCollation>
      <columnFullText>N</columnFullText>
      <columnVisibleWidth>%ISD_DEFAULT%</columnVisibleWidth>
      <columnTableAliasName>
      </columnTableAliasName>
      <applyLabelText>Y</applyLabelText>
    </Column>
    <Column InternalName="72" Priority="73" ColumnNum="72">
      <columnName>equipment_inventory_pic10_name</columnName>
      <columnUIName>%ISD_DEFAULT%</columnUIName>
      <columnType>String</columnType>
      <columnDBType>varchar</columnDBType>
      <columnLengthSet>50</columnLengthSet>
      <columnDefault>
      </columnDefault>
      <columnDBDefault>
      </columnDBDefault>
      <columnIndex>N</columnIndex>
      <columnUnique>N</columnUnique>
      <columnFunction>
      </columnFunction>
      <columnDBFormat>
      </columnDBFormat>
      <columnPK>N</columnPK>
      <columnPermanent>N</columnPermanent>
      <columnComputed>N</columnComputed>
      <columnIdentity>N</columnIdentity>
      <columnReadOnly>N</columnReadOnly>
      <columnRequired>N</columnRequired>
      <columnNotNull>N</columnNotNull>
      <columnCaseSensitive Source="Database">N</columnCaseSensitive>
      <columnCollation>SQL_Latin1_General_CP1_CI_AS</columnCollation>
      <columnFullText>N</columnFullText>
      <columnVisibleWidth>%ISD_DEFAULT%</columnVisibleWidth>
      <columnTableAliasName>
      </columnTableAliasName>
      <applyLabelText>Y</applyLabelText>
    </Column>
    <Column InternalName="73" Priority="74" ColumnNum="73">
      <columnName>encoded_inventory_id</columnName>
      <columnUIName>%ISD_DEFAULT%</columnUIName>
      <columnType>String</columnType>
      <columnDBType>varchar</columnDBType>
      <columnLengthSet>100</columnLengthSet>
      <columnDefault>
      </columnDefault>
      <columnDBDefault>
      </columnDBDefault>
      <columnIndex>N</columnIndex>
      <columnUnique>N</columnUnique>
      <columnFunction>
      </columnFunction>
      <columnDBFormat>
      </columnDBFormat>
      <columnPK>N</columnPK>
      <columnPermanent>N</columnPermanent>
      <columnComputed>N</columnComputed>
      <columnIdentity>N</columnIdentity>
      <columnReadOnly>N</columnReadOnly>
      <columnRequired>N</columnRequired>
      <columnNotNull>N</columnNotNull>
      <columnCaseSensitive Source="Database">N</columnCaseSensitive>
      <columnCollation>SQL_Latin1_General_CP1_CI_AS</columnCollation>
      <columnFullText>N</columnFullText>
      <columnVisibleWidth>%ISD_DEFAULT%</columnVisibleWidth>
      <columnTableAliasName>
      </columnTableAliasName>
      <applyLabelText>Y</applyLabelText>
    </Column>
    <Column InternalName="74" Priority="75" ColumnNum="74">
      <columnName>exchange_listing_id</columnName>
      <columnUIName>%ISD_DEFAULT%</columnUIName>
      <columnType>Number</columnType>
      <columnDBType>numeric</columnDBType>
      <columnLengthSet>18.0</columnLengthSet>
      <columnDefault>
      </columnDefault>
      <columnDBDefault>
      </columnDBDefault>
      <columnIndex>N</columnIndex>
      <columnUnique>N</columnUnique>
      <columnFunction>
      </columnFunction>
      <columnDBFormat>
      </columnDBFormat>
      <columnPK>N</columnPK>
      <columnPermanent>N</columnPermanent>
      <columnComputed>N</columnComputed>
      <columnIdentity>N</columnIdentity>
      <columnReadOnly>N</columnReadOnly>
      <columnRequired>N</columnRequired>
      <columnNotNull>N</columnNotNull>
      <columnCaseSensitive>N</columnCaseSensitive>
      <columnCollation>
      </columnCollation>
      <columnFullText>N</columnFullText>
      <columnVisibleWidth>%ISD_DEFAULT%</columnVisibleWidth>
      <columnTableAliasName>
      </columnTableAliasName>
      <applyLabelText>Y</applyLabelText>
    </Column>
    <Column InternalName="75" Priority="76" ColumnNum="75">
      <columnName>Expr1</columnName>
      <columnUIName>%ISD_DEFAULT%</columnUIName>
      <columnType>String</columnType>
      <columnDBType>varchar</columnDBType>
      <columnLengthSet>5</columnLengthSet>
      <columnDefault>
      </columnDefault>
      <columnDBDefault>
      </columnDBDefault>
      <columnIndex>N</columnIndex>
      <columnUnique>N</columnUnique>
      <columnFunction>
      </columnFunction>
      <columnDBFormat>
      </columnDBFormat>
      <columnPK>N</columnPK>
      <columnPermanent>N</columnPermanent>
      <columnComputed>N</columnComputed>
      <columnIdentity>N</columnIdentity>
      <columnReadOnly>N</columnReadOnly>
      <columnRequired>N</columnRequired>
      <columnNotNull>N</columnNotNull>
      <columnCaseSensitive Source="Database">N</columnCaseSensitive>
      <columnCollation>SQL_Latin1_General_CP1_CI_AS</columnCollation>
      <columnFullText>N</columnFullText>
      <columnVisibleWidth>%ISD_DEFAULT%</columnVisibleWidth>
      <columnTableAliasName>
      </columnTableAliasName>
      <applyLabelText>Y</applyLabelText>
    </Column>
    <Column InternalName="76" Priority="77" ColumnNum="76">
      <columnName>inventory_public</columnName>
      <columnUIName>%ISD_DEFAULT%</columnUIName>
      <columnType>Boolean</columnType>
      <columnDBType>bit</columnDBType>
      <columnLengthSet>
      </columnLengthSet>
      <columnDefault>
      </columnDefault>
      <columnDBDefault>
      </columnDBDefault>
      <columnIndex>N</columnIndex>
      <columnUnique>N</columnUnique>
      <columnFunction>
      </columnFunction>
      <columnDBFormat>
      </columnDBFormat>
      <columnPK>N</columnPK>
      <columnPermanent>N</columnPermanent>
      <columnComputed>N</columnComputed>
      <columnIdentity>N</columnIdentity>
      <columnReadOnly>N</columnReadOnly>
      <columnRequired>N</columnRequired>
      <columnNotNull>N</columnNotNull>
      <columnCaseSensitive>N</columnCaseSensitive>
      <columnCollation>
      </columnCollation>
      <columnFullText>N</columnFullText>
      <columnVisibleWidth>%ISD_DEFAULT%</columnVisibleWidth>
      <columnTableAliasName>
      </columnTableAliasName>
      <applyLabelText>Y</applyLabelText>
    </Column>
    <Column InternalName="77" Priority="78" ColumnNum="77">
      <columnName>inservice</columnName>
      <columnUIName>%ISD_DEFAULT%</columnUIName>
      <columnType>Date</columnType>
      <columnDBType>date</columnDBType>
      <columnLengthSet>
      </columnLengthSet>
      <columnDefault>
      </columnDefault>
      <columnDBDefault>
      </columnDBDefault>
      <columnIndex>N</columnIndex>
      <columnUnique>N</columnUnique>
      <columnFunction>notrim</columnFunction>
      <columnFormat>d</columnFormat>
      <columnDBFormat>d</columnDBFormat>
      <columnPK>N</columnPK>
      <columnPermanent>N</columnPermanent>
      <columnComputed>N</columnComputed>
      <columnIdentity>N</columnIdentity>
      <columnReadOnly>N</columnReadOnly>
      <columnRequired>N</columnRequired>
      <columnNotNull>N</columnNotNull>
      <columnCaseSensitive>N</columnCaseSensitive>
      <columnCollation>
      </columnCollation>
      <columnFullText>N</columnFullText>
      <columnVisibleWidth>%ISD_DEFAULT%</columnVisibleWidth>
      <columnTableAliasName>
      </columnTableAliasName>
      <applyLabelText>Y</applyLabelText>
    </Column>
    <Column InternalName="78" Priority="79" ColumnNum="78">
      <columnName>listing_id</columnName>
      <columnUIName>%ISD_DEFAULT%</columnUIName>
      <columnType>Number</columnType>
      <columnDBType>numeric</columnDBType>
      <columnLengthSet>18.0</columnLengthSet>
      <columnDefault>
      </columnDefault>
      <columnDBDefault>
      </columnDBDefault>
      <columnIndex>N</columnIndex>
      <columnUnique>N</columnUnique>
      <columnFunction>
      </columnFunction>
      <columnDBFormat>
      </columnDBFormat>
      <columnPK>N</columnPK>
      <columnPermanent>N</columnPermanent>
      <columnComputed>N</columnComputed>
      <columnIdentity>N</columnIdentity>
      <columnReadOnly>N</columnReadOnly>
      <columnRequired>Y</columnRequired>
      <columnNotNull>Y</columnNotNull>
      <columnCaseSensitive>N</columnCaseSensitive>
      <columnCollation>
      </columnCollation>
      <columnFullText>N</columnFullText>
      <columnVisibleWidth>%ISD_DEFAULT%</columnVisibleWidth>
      <columnTableAliasName>
      </columnTableAliasName>
      <applyLabelText>Y</applyLabelText>
    </Column>
    <Column InternalName="79" Priority="80" ColumnNum="79">
      <columnName>inventory_id</columnName>
      <columnUIName>%ISD_DEFAULT%</columnUIName>
      <columnType>Number</columnType>
      <columnDBType>numeric</columnDBType>
      <columnLengthSet>18.0</columnLengthSet>
      <columnDefault>
      </columnDefault>
      <columnDBDefault>
      </columnDBDefault>
      <columnIndex>N</columnIndex>
      <columnUnique>N</columnUnique>
      <columnFunction>
      </columnFunction>
      <columnDBFormat>
      </columnDBFormat>
      <columnPK>N</columnPK>
      <columnPermanent>N</columnPermanent>
      <columnComputed>N</columnComputed>
      <columnIdentity>N</columnIdentity>
      <columnReadOnly>N</columnReadOnly>
      <columnRequired>Y</columnRequired>
      <columnNotNull>Y</columnNotNull>
      <columnCaseSensitive>N</columnCaseSensitive>
      <columnCollation>
      </columnCollation>
      <columnFullText>N</columnFullText>
      <columnVisibleWidth>%ISD_DEFAULT%</columnVisibleWidth>
      <columnTableAliasName>
      </columnTableAliasName>
      <applyLabelText>Y</applyLabelText>
    </Column>
    <Column InternalName="80" Priority="81" ColumnNum="80">
      <columnName>exchange_listing_date</columnName>
      <columnUIName>%ISD_DEFAULT%</columnUIName>
      <columnType>Date</columnType>
      <columnDBType>date</columnDBType>
      <columnLengthSet>
      </columnLengthSet>
      <columnDefault>
      </columnDefault>
      <columnDBDefault>
      </columnDBDefault>
      <columnIndex>N</columnIndex>
      <columnUnique>N</columnUnique>
      <columnFunction>notrim</columnFunction>
      <columnFormat>d</columnFormat>
      <columnDBFormat>d</columnDBFormat>
      <columnPK>N</columnPK>
      <columnPermanent>N</columnPermanent>
      <columnComputed>N</columnComputed>
      <columnIdentity>N</columnIdentity>
      <columnReadOnly>N</columnReadOnly>
      <columnRequired>N</columnRequired>
      <columnNotNull>N</columnNotNull>
      <columnCaseSensitive>N</columnCaseSensitive>
      <columnCollation>
      </columnCollation>
      <columnFullText>N</columnFullText>
      <columnVisibleWidth>%ISD_DEFAULT%</columnVisibleWidth>
      <columnTableAliasName>
      </columnTableAliasName>
      <applyLabelText>Y</applyLabelText>
    </Column>
    <Column InternalName="81" Priority="82" ColumnNum="81">
      <columnName>exchange_listed_by</columnName>
      <columnUIName>%ISD_DEFAULT%</columnUIName>
      <columnType>Number</columnType>
      <columnDBType>int</columnDBType>
      <columnLengthSet>10.0</columnLengthSet>
      <columnDefault>
      </columnDefault>
      <columnDBDefault>
      </columnDBDefault>
      <columnIndex>N</columnIndex>
      <columnUnique>N</columnUnique>
      <columnFunction>
      </columnFunction>
      <columnDBFormat>
      </columnDBFormat>
      <columnPK>N</columnPK>
      <columnPermanent>N</columnPermanent>
      <columnComputed>N</columnComputed>
      <columnIdentity>N</columnIdentity>
      <columnReadOnly>N</columnReadOnly>
      <columnRequired>N</columnRequired>
      <columnNotNull>N</columnNotNull>
      <columnCaseSensitive>N</columnCaseSensitive>
      <columnCollation>
      </columnCollation>
      <columnFullText>N</columnFullText>
      <columnVisibleWidth>%ISD_DEFAULT%</columnVisibleWidth>
      <columnTableAliasName>
      </columnTableAliasName>
      <applyLabelText>Y</applyLabelText>
    </Column>
    <Column InternalName="82" Priority="83" ColumnNum="82">
      <columnName>exchange_listing_active</columnName>
      <columnUIName>%ISD_DEFAULT%</columnUIName>
      <columnType>Boolean</columnType>
      <columnDBType>bit</columnDBType>
      <columnLengthSet>
      </columnLengthSet>
      <columnDefault>
      </columnDefault>
      <columnDBDefault>
      </columnDBDefault>
      <columnIndex>N</columnIndex>
      <columnUnique>N</columnUnique>
      <columnFunction>
      </columnFunction>
      <columnDBFormat>
      </columnDBFormat>
      <columnPK>N</columnPK>
      <columnPermanent>N</columnPermanent>
      <columnComputed>N</columnComputed>
      <columnIdentity>N</columnIdentity>
      <columnReadOnly>N</columnReadOnly>
      <columnRequired>N</columnRequired>
      <columnNotNull>N</columnNotNull>
      <columnCaseSensitive>N</columnCaseSensitive>
      <columnCollation>
      </columnCollation>
      <columnFullText>N</columnFullText>
      <columnVisibleWidth>%ISD_DEFAULT%</columnVisibleWidth>
      <columnTableAliasName>
      </columnTableAliasName>
      <applyLabelText>Y</applyLabelText>
    </Column>
    <Column InternalName="83" Priority="84" ColumnNum="83">
      <columnName>exchange_listing_custno</columnName>
      <columnUIName>%ISD_DEFAULT%</columnUIName>
      <columnType>Number</columnType>
      <columnDBType>int</columnDBType>
      <columnLengthSet>10.0</columnLengthSet>
      <columnDefault>
      </columnDefault>
      <columnDBDefault>
      </columnDBDefault>
      <columnIndex>N</columnIndex>
      <columnUnique>N</columnUnique>
      <columnFunction>
      </columnFunction>
      <columnDBFormat>
      </columnDBFormat>
      <columnPK>N</columnPK>
      <columnPermanent>N</columnPermanent>
      <columnComputed>N</columnComputed>
      <columnIdentity>N</columnIdentity>
      <columnReadOnly>N</columnReadOnly>
      <columnRequired>N</columnRequired>
      <columnNotNull>N</columnNotNull>
      <columnCaseSensitive>N</columnCaseSensitive>
      <columnCollation>
      </columnCollation>
      <columnFullText>N</columnFullText>
      <columnVisibleWidth>%ISD_DEFAULT%</columnVisibleWidth>
      <columnTableAliasName>
      </columnTableAliasName>
      <applyLabelText>Y</applyLabelText>
    </Column>
    <Column InternalName="84" Priority="85" ColumnNum="84">
      <columnName>dayslisted</columnName>
      <columnUIName>%ISD_DEFAULT%</columnUIName>
      <columnType>Number</columnType>
      <columnDBType>int</columnDBType>
      <columnLengthSet>10.0</columnLengthSet>
      <columnDefault>
      </columnDefault>
      <columnDBDefault>
      </columnDBDefault>
      <columnIndex>N</columnIndex>
      <columnUnique>N</columnUnique>
      <columnFunction>
      </columnFunction>
      <columnDBFormat>
      </columnDBFormat>
      <columnPK>N</columnPK>
      <columnPermanent>N</columnPermanent>
      <columnComputed>N</columnComputed>
      <columnIdentity>N</columnIdentity>
      <columnReadOnly>N</columnReadOnly>
      <columnRequired>N</columnRequired>
      <columnNotNull>N</columnNotNull>
      <columnCaseSensitive>N</columnCaseSensitive>
      <columnCollation>
      </columnCollation>
      <columnFullText>N</columnFullText>
      <columnVisibleWidth>%ISD_DEFAULT%</columnVisibleWidth>
      <columnTableAliasName>
      </columnTableAliasName>
      <applyLabelText>Y</applyLabelText>
    </Column>
  </ColumnDefinition>
  <TableName>vw_facility_exchange_listing</TableName>
  <Version>
  </Version>
  <Owner>dbo</Owner>
  <TableAliasName>vw_facility_exchange_listing_</TableAliasName>
  <ConnectionName>DatabaseAYS_OEM</ConnectionName>
  <InUse>N</InUse>
  <PagingMethod>RowNum</PagingMethod>
  <canCreateRecords Source="Database">N</canCreateRecords>
  <canEditRecords Source="Database">N</canEditRecords>
  <canDeleteRecords Source="Database">N</canDeleteRecords>
  <canViewRecords Source="Database">N</canViewRecords>
  <AppShortName>OEMConversion</AppShortName>
  <FolderName>vw_facility_exchange_listing</FolderName>
  <MenuName>Facility Exchange Listing</MenuName>
  <QSPath>../vw_facility_exchange_listing/Vw-facility-exchange-listing-QuickSelector.aspx</QSPath>
  <TableCodeName>Vw_facility_exchange_listing</TableCodeName>
</XMLDefinition>